Workbook

Sheet Tableau de bord
A1: AfricaVET — couverture éditoriale des 55 pays de l’Union africaine
A2: Inventaire exhaustif des articles au 25 août 2026 | Base vérifiable et priorités de rééquilibrage
A4: =COUNTA(Corpus!$A$2:$A$1045) -> 1044 | F4: =COUNTIF(Corpus!$I$2:$I$1045,"National") -> 551 | K4: =COUNTIF('Classement 55'!$D$5:$D$59,">0") -> 51 | P4: =COUNTIF('Classement 55'!$D$5:$D$59,0) -> 4
A8: Articles publiés | F8: Articles nationaux | K8: Pays couverts | P8: Pays sans article
A11: Pays | B11: Articles nationaux | N11: Région | O11: Articles
A12: ='Classement 55'!B5 -> Cameroun | B12: ='Classement 55'!D5 -> 112 | N12: ='Analyse régions'!A5 -> Afrique centrale | O12: ='Analyse régions'!C5 -> 163
A13: ='Classement 55'!B6 -> Sénégal | B13: ='Classement 55'!D6 -> 74 | N13: ='Analyse régions'!A6 -> Afrique de l'Ouest | O13: ='Analyse régions'!C6 -> 214
A14: ='Classement 55'!B7 -> Côte d’Ivoire | B14: ='Classement 55'!D7 -> 46 | N14: ='Analyse régions'!A7 -> Afrique de l'Est | O14: ='Analyse régions'!C7 -> 96
A15: ='Classement 55'!B8 -> Kenya | B15: ='Classement 55'!D8 -> 39 | N15: ='Analyse régions'!A8 -> Afrique australe | O15: ='Analyse régions'!C8 -> 41
A16: ='Classement 55'!B9 -> Burkina Faso | B16: ='Classement 55'!D9 -> 24 | N16: ='Analyse régions'!A9 -> Afrique du Nord | O16: ='Analyse régions'!C9 -> 37
A17: ='Classement 55'!B10 -> Afrique du Sud | B17: ='Classement 55'!D10 -> 23
A18: ='Classement 55'!B11 -> Nigeria | B18: ='Classement 55'!D11 -> 23
A19: ='Classement 55'!B12 -> Tchad | B19: ='Classement 55'!D12 -> 20
A20: ='Classement 55'!B13 -> RDC | B20: ='Classement 55'!D13 -> 16
A21: ='Classement 55'!B14 -> Maroc | B21: ='Classement 55'!D14 -> 15
A22: ='Classement 55'!B15 -> Togo | B22: ='Classement 55'!D15 -> 12
A23: ='Classement 55'!B16 -> Tanzanie | B23: ='Classement 55'!D16 -> 11
A24: ='Classement 55'!B17 -> Niger | B24: ='Classement 55'!D17 -> 10
A25: ='Classement 55'!B18 -> Ouganda | B25: ='Classement 55'!D18 -> 10
A26: ='Classement 55'!B19 -> Rwanda | B26: ='Classement 55'!D19 -> 10
A32: Constats clés et implications éditoriales | B32: Constats clés et implications éditoriales | C32: Constats clés et implications éditoriales | D32: Constats clés et implications éditoriales | E32: Constats clés et implications éditoriales | F32: Constats clés et implications éditoriales | G32: Constats clés et implications éditoriales | H32: Constats clés et implications éditoriales | I32: Constats clés et implications éditoriales | J32: Constats clés et implications éditoriales | K32: Constats clés et implications éditoriales | L32: Constats clés et implications éditoriales | M32: Constats clés et implications éditoriales | N32: Constats clés et implications éditoriales | O32: Constats clés et implications éditoriales | P32: Constats clés et implications éditoriales | Q32: Constats clés et implications éditoriales | R32: Constats clés et implications éditoriales | S32: Constats clés et implications éditoriales | T32: Constats clés et implications éditoriales
A34: • 53,5 % des articles nationaux sont concentrés sur cinq pays; les dix premiers représentent 71,1 %. • 4 États membres n’ont aucun article national identifié : Libye, RASD / Sahara occidental, Sao Tomé-et-Principe, Érythrée. • L’Afrique australe et l’Afrique du Nord affichent les plus faibles moyennes par pays. • Le champ pays du site n’est rempli que pour 61 articles sur 1 044 : la taxonomie géographique doit devenir obligatoire. • 202 attributions restent à vérifier, principalement des contenus génériques, mondiaux ou sans ancrage géographique explicite.
A42: Mesures de concentration | B42: Mesures de concentration | C42: Mesures de concentration | D42: Mesures de concentration | E42: Mesures de concentration | F42: Mesures de concentration | G42: Mesures de concentration | H42: Mesures de concentration | I42: Mesures de concentration | J42: Mesures de concentration | L42: Priorité d’action | M42: Priorité d’action | N42: Priorité d’action | O42: Priorité d’action | P42: Priorité d’action | Q42: Priorité d’action | R42: Priorité d’action | S42: Priorité d’action | T42: Priorité d’action
A43: Indicateur | B43: Valeur | L43: 1. Ouvrir une série “55 pays, 55 regards” en commençant par les 4 pays absents. 2. Fixer un plancher trimestriel pour les 35 pays à couverture nulle, très faible ou faible. 3. Rééquilibrer les sujets : faune/conservation ne représente que 15 articles, contre 224 pour One Health/zoonoses/santé publique. 4. Rendre obligatoires pays, région, langue d’origine et macrothème dans le CMS. 5. Réviser en priorité les 50 attributions nationales déduites uniquement du début du texte.
A44: Part des 2 premiers pays | B44: 0.33756806
A45: Part des 5 premiers pays | B45: 0.5353902
A46: Part des 10 premiers pays | B46: 0.71143376
A47: Indice de Gini (55 pays) | B47: 0.69341693

Sheet Vue journalistique
A1: AfricaVET — tableau de pilotage journalistique
A2: Auteurs, audience, impact, qualité éditoriale et priorités d’amélioration | Photographie au 25 août 2026
A4: 1044 | F4: 22786 | K4: 5 | P4: 21.829502
A8: Articles analysés | F8: Vues cumulées | K8: Auteurs normalisés | P8: Score moyen de complétude
A10: Auteurs — production et audience | B10: Auteurs — production et audience | C10: Auteurs — production et audience | D10: Auteurs — production et audience | E10: Auteurs — production et audience | F10: Auteurs — production et audience | G10: Auteurs — production et audience | H10: Auteurs — production et audience | N10: Articles au plus fort impact relatif | O10: Articles au plus fort impact relatif | P10: Articles au plus fort impact relatif | Q10: Articles au plus fort impact relatif | R10: Articles au plus fort impact relatif | S10: Articles au plus fort impact relatif | T10: Articles au plus fort impact relatif
A11: Auteur | B11: Articles | C11: Vues | D11: Vues/article | N11: Rang | O11: Article | P11: Auteur | Q11: Vues | R11: Vues/jour | S11: Score | T11: Niveau
A12: =Auteurs!A5 -> Malick Kane | B12: =Auteurs!B5 -> 798 | C12: =Auteurs!D5 -> 17485 | D12: =Auteurs!F5 -> 21.911028 | N12: 1 | O12: Coccidiose chez les poulets : ces signes discrets qui peu… | P12: Malick Kane | Q12: 181 | R12: 30.166667 | S12: 99.9 | T12: Très fort
A13: =Auteurs!A6 -> Flora J. Ingah | B13: =Auteurs!B6 -> 87 | C13: =Auteurs!D6 -> 1758 | D13: =Auteurs!F6 -> 20.206897 | N13: 2 | O13: Burkina Faso : l’opération « Zéro poulailler vide » veut … | P13: Malick Kane | Q13: 121 | R13: 24.2 | S13: 99.7 | T13: Très fort
A14: =Auteurs!A7 -> Mac Juliette Johngwe | B14: =Auteurs!B7 -> 85 | C14: =Auteurs!D7 -> 2074 | D14: =Auteurs!F7 -> 24.4 | N14: 3 | O14: PPR : les « épisystèmes », un levier stratégique pour le … | P14: Malick Kane | Q14: 91 | R14: 15.166667 | S14: 99.3 | T14: Très fort
A15: =Auteurs!A8 -> Simon Yaya | B15: =Auteurs!B8 -> 67 | C15: =Auteurs!D8 -> 1407 | D15: =Auteurs!F8 -> 21 | N15: 4 | O15: ZLECAf : les ministres africains veulent accélérer le com… | P15: Malick Kane | Q15: 226 | R15: 5.65 | S15: 99.2 | T15: Très fort
A16: =Auteurs!A9 -> Absan Bibou | B16: =Auteurs!B9 -> 7 | C16: =Auteurs!D9 -> 62 | D16: =Auteurs!F9 -> 8.8571429 | N16: 5 | O16: Cameroun : 93 stages ouverts dans des projets financés pa… | P16: Malick Kane | Q16: 75 | R16: 15 | S16: 99 | T16: Très fort
N17: 6 | O17: Pêche en Afrique : femmes et jeunes, piliers encore invis… | P17: Malick Kane | Q17: 111 | R17: 3.5806452 | S17: 98.3 | T17: Très fort
N18: 7 | O18: Peste des petits ruminants : symptômes, transmission, dia… | P18: Malick Kane | Q18: 145 | R18: 3.1521739 | S18: 98.2 | T18: Très fort
N19: 8 | O19: Sénégal : à Mbao, 1 000 ruches pour donner un nouvel élan… | P19: Malick Kane | Q19: 89 | R19: 3.56 | S19: 98 | T19: Très fort
N20: 9 | O20: Sudan: Vaccinating livestock amid conflict, a cross-borde… | P20: Malick Kane | Q20: 78 | R20: 3.25 | S20: 97.8 | T20: Très fort
N21: 10 | O21: Fientes anormales chez les poulets : ce que leur couleur … | P21: Malick Kane | Q21: 66 | R21: 5.5 | S21: 97.7 | T21: Très fort
A28: Constats spécialisés | B28: Constats spécialisés | C28: Constats spécialisés | D28: Constats spécialisés | E28: Constats spécialisés | F28: Constats spécialisés | G28: Constats spécialisés | H28: Constats spécialisés | I28: Constats spécialisés | J28: Constats spécialisés | K28: Constats spécialisés | L28: Constats spécialisés | M28: Constats spécialisés | N28: Constats spécialisés | O28: Constats spécialisés | P28: Constats spécialisés | Q28: Constats spécialisés | R28: Constats spécialisés | S28: Constats spécialisés | T28: Constats spécialisés
A29: • Malick Kane signe 76,4 % du corpus : la capacité de production est forte, mais la dépendance éditoriale est élevée. • Les 301 articles publiés en 2026 cumulent 11 003 vues, soit 48,3 % des vues du corpus. • L’article médian compte 16,5 vues; les dix articles les plus vus représentent 5,8 % des vues, ce qui indique une audience assez diffuse. • 385 articles sont détectés en anglais alors que la métadonnée de langue d’origine reste renseignée en français : le pilotage multilingue est faussé. • La complétude moyenne des éléments journalistiques et SEO n’est que de 21,8 / 100; ce score mesure les champs et la présentation, jamais la qualité du fond.
A38: Priorités de rédaction | B38: Priorités de rédaction | C38: Priorités de rédaction | D38: Priorités de rédaction | E38: Priorités de rédaction | F38: Priorités de rédaction | G38: Priorités de rédaction | H38: Priorités de rédaction | I38: Priorités de rédaction | J38: Priorités de rédaction | L38: Mesure d’audience à connecter | M38: Mesure d’audience à connecter | N38: Mesure d’audience à connecter | O38: Mesure d’audience à connecter | P38: Mesure d’audience à connecter | Q38: Mesure d’audience à connecter | R38: Mesure d’audience à connecter | S38: Mesure d’audience à connecter | T38: Mesure d’audience à connecter
A39: 1. Diversifier progressivement les signatures et formaliser les domaines de responsabilité de chaque auteur. 2. Fixer une check-list de publication : pays/région, langue, sources, crédit image, méta-titre, méta-description et validation. 3. Distinguer les formats : alerte, article d’actualité, analyse, guide pratique, entretien, reportage et dossier. 4. Suivre chaque mois le rendement par thème, pays, langue et auteur sans confondre volume et impact. 5. Conserver les titres complets dans le CMS, mais tester une longueur SEO plus resserrée pour l’affichage et le partage. | L39: Les vues de l’API sont cumulées par article. Elles ne remplacent pas les visiteurs uniques, les sessions, les sources de trafic, le temps d’engagement, la localisation de l’audience ou les conversions. Priorité : connecter GA4 ou Matomo, Search Console et des liens UTM cohérents pour Facebook, X, WhatsApp et la newsletter. Le tableau pourra alors mesurer la portée panafricaine, l’acquisition, la fidélisation et les conversions réelles.

Sheet Plan mise en œuvre
A1: AfricaVET — plan détaillé de mise en œuvre
A2: Feuille de route opérationnelle sur 12 mois | Responsables, échéances, livrables, KPI, dépendances et revues
A4: 24 | E4: 10 | I4: 12 | M4: 4
A8: Actions planifiées | E8: Actions des 30 premiers jours | I8: Horizon de transformation | M8: Revues stratégiques/an
A10: N° | B10: Phase | C10: Axe | D10: Action détaillée | E10: Priorité | F10: Responsable proposé | G10: Début | H10: Échéance | I10: Durée (j) | J10: Livrable attendu | K10: Indicateur de succès | L10: Cible | M10: Dépendances | N10: Revue / validation | O10: Statut
A11: 1 | B11: J0–J7 | C11: Gouvernance | D11: Mettre en place un comité éditorial restreint et valider les rôles décisionnels. | E11: P0 | F11: Direction / Rédaction en chef | G11: 46260 | H11: 46266 | I11: =H11-G11+1 -> 7 | J11: Note de gouvernance et calendrier des réunions | K11: Comité désigné et première réunion tenue | L11: 100 % | M11: Disponibilité des responsables | N11: Direction | O11: À lancer
A12: 2 | B12: J0–J7 | C12: Gouvernance | D12: Valider la matrice RACI pour commande, validation scientifique, publication, correction et retrait. | E12: P0 | F12: Rédaction en chef | G12: 46260 | H12: 46268 | I12: =H12-G12+1 -> 9 | J12: Matrice RACI approuvée | K12: Aucune étape critique sans responsable | L12: 100 % | M12: Action 1 | N12: Comité éditorial | O12: À lancer
A13: 3 | B13: J0–J30 | C13: CMS / métadonnées | D13: Rendre obligatoires pays ou région, langue réelle, auteur normalisé, catégorie, sources, crédit image, méta-titre et méta-description. | E13: P0 | F13: Webmaster / CMS | G13: 46261 | H13: 46280 | I13: =H13-G13+1 -> 20 | J13: Formulaire CMS révisé avec contrôles bloquants | K13: Nouveaux articles complets sur les champs obligatoires | L13: 100 % | M13: Accès technique au CMS | N13: Rédaction en chef | O13: À lancer
A14: 4 | B14: J0–J15 | C14: Auteurs | D14: Nettoyer les signatures, créer une fiche normalisée par auteur et éviter les doublons d’espacement ou d’orthographe. | E14: P0 | F14: Webmaster + Rédaction | G14: 46261 | H14: 46270 | I14: =H14-G14+1 -> 10 | J14: Référentiel unique des auteurs | K14: 5 auteurs actuels correctement normalisés | L14: 100 % | M14: Liste des comptes CMS | N14: Rédaction en chef | O14: À lancer
A15: 5 | B15: J0–J30 | C15: Audience | D15: Auditer puis installer ou fiabiliser GA4 ou Matomo, Search Console et les événements de conversion. | E15: P0 | F15: Responsable analytics / Webmaster | G15: 46261 | H15: 46280 | I15: =H15-G15+1 -> 20 | J15: Plan de marquage et tableau de contrôle | K15: Visiteurs, sessions, engagement et conversions mesurables | L15: Suivi actif | M15: Accès domaine et consentement cookies | N15: Direction | O15: À lancer
A16: 6 | B16: J0–J15 | C16: Distribution | D16: Adopter une convention UTM unique pour Facebook, X, WhatsApp, newsletter et partenaires. | E16: P0 | F16: Audience / Réseaux sociaux | G16: 46262 | H16: 46272 | I16: =H16-G16+1 -> 11 | J16: Guide UTM et générateur de liens | K16: Liens sociaux conformes | L16: ≥ 80 % | M16: Action 5 | N16: Rédaction en chef | O16: À lancer
A17: 7 | B17: J0–J15 | C17: Qualité | D17: Instaurer une check-list prépublication et une double validation pour les contenus sanitaires, scientifiques ou sensibles. | E17: P0 | F17: Rédaction en chef + Référent scientifique | G17: 46260 | H17: 46270 | I17: =H17-G17+1 -> 11 | J17: Check-list, journal de validation et règles d’escalade | K17: Contenus sensibles validés avant publication | L17: 100 % | M17: Disponibilité du référent | N17: Comité éditorial | O17: À lancer
A18: 8 | B18: J0–J30 | C18: Couverture UA | D18: Commander et publier un premier article pour la Libye, la RASD/Sahara occidental, Sao Tomé-et-Principe et l’Érythrée. | E18: P0 | F18: Coordination éditoriale | G18: 46261 | H18: 46295 | I18: =H18-G18+1 -> 35 | J18: Quatre articles nationaux vérifiés | K18: Pays UA couverts | L18: 55/55 | M18: Accès à des sources fiables | N18: Comité éditorial | O18: À lancer
A19: 9 | B19: J0–J30 | C19: Multilingue | D19: Corriger le paramétrage de langue d’origine et traiter les 385 incohérences FR/EN identifiées. | E19: P0 | F19: Webmaster + Édition linguistique | G19: 46262 | H19: 46295 | I19: =H19-G19+1 -> 34 | J19: Métadonnées linguistiques corrigées | K19: Incohérences restantes | L19: 0 | M19: Action 3 | N19: Rédaction en chef | O19: À lancer
A20: 10 | B20: J0–J30 | C20: Éthique / corrections | D20: Publier une politique de correction, mise à jour, droit de réponse, conflits d’intérêts et contenus sponsorisés. | E20: P0 | F20: Direction / Rédaction en chef | G20: 46262 | H20: 46285 | I20: =H20-G20+1 -> 24 | J20: Politique publique et procédure interne | K20: Corrections tracées avec date et motif | L20: 100 % | M20: Validation juridique si nécessaire | N20: Direction | O20: À lancer
A21: 11 | B21: J31–J90 | C21: Archives | D21: Corriger en priorité les métadonnées des 200 articles les plus vus et des contenus sanitaires à fort risque. | E21: P1 | F21: Équipe CMS / Éditeurs | G21: 46286 | H21: 46356 | I21: =H21-G21+1 -> 71 | J21: Lot de 200 articles remis à niveau | K21: Articles prioritaires complétés | L21: 200 | M21: Actions 3 et 7 | N21: Rédaction en chef | O21: À lancer
A22: 12 | B22: J31–J90 | C22: Réseau | D22: Recruter ou formaliser au moins cinq correspondants régionaux et clarifier rémunération, commande et validation. | E22: P1 | F22: Direction / Coordination Afrique | G22: 46266 | H22: 46326 | I22: =H22-G22+1 -> 61 | J22: Fiches de mission et vivier de correspondants | K22: Régions UA avec point focal actif | L22: 5/5 | M22: Budget et contrats | N22: Direction | O22: À lancer
... A34: 24 | B34: M7–M12 | C34: Impact / pérennité | D34: Publier un rapport annuel d’impact éditorial et arrêter le plan de ressources, partenariats et revenus de l’année suivante. | E34: P3 | F34: Direction + Rédaction | G34: 46569 | H34: 46624 | I34: =H34-G34+1 -> 56 | J34: Rapport annuel et plan 2027–2028 | K34: Décisions documentées et budget validé | L34: 1 rapport | M34: Données annuelles complètes | N34: Direction | O34: À lancer

Sheet Plan 90 jours
A1: AfricaVET — calendrier opérationnel des 90 premiers jours
A2: Séquençage hebdomadaire du 26 août au 30 novembre 2026 | Chaque semaine se termine par une preuve vérifiable
A4: Semaine | B4: Début | C4: Fin | D4: Objectif principal | E4: Actions essentielles | F4: Responsable proposé | G4: Livrable | H4: Preuve / KPI | I4: Point de revue | J4: Statut
A5: S0 | B5: 46260 | C5: 46264 | D5: Lancer la gouvernance | E5: Désigner le comité éditorial; valider le principe du RACI; geler les règles de nommage des auteurs. | F5: Direction / Rédaction en chef | G5: Note de lancement | H5: Comité nommé; réunion programmée | I5: 30 août | J5: À lancer
A6: S1 | B6: 46265 | C6: 46271 | D6: Sécuriser la publication | E6: Adopter check-list, double validation, politique de correction provisoire et référentiel auteurs. | F6: Rédaction en chef | G6: Pack qualité v1 | H6: 100 % des nouveaux contenus utilisent la check-list | I6: 6 septembre | J6: À lancer
A7: S2 | B7: 46272 | C7: 46278 | D7: Normaliser diffusion et analytics | E7: Finaliser UTM; auditer GA4/Matomo; définir conversions et tableau de bord minimum. | F7: Audience / Webmaster | G7: Plan de marquage | H7: UTM actifs; anomalies analytics documentées | I7: 13 septembre | J7: À lancer
A8: S3 | B8: 46279 | C8: 46285 | D8: Corriger le CMS | E8: Activer les champs obligatoires; tester langue, pays/région, sources, crédit image et SEO. | F8: Webmaster / CMS | G8: CMS v1 | H8: Publication bloquée si champ critique absent | I8: 20 septembre | J8: À lancer
A9: S4 | B9: 46286 | C9: 46292 | D9: Répartir les responsabilités | E9: Entretiens auteurs; validation des portefeuilles; confirmation des auteurs inactifs et besoins de recrutement. | F9: Rédaction en chef | G9: Plans individuels | H9: 5 décisions de positionnement documentées | I9: 27 septembre | J9: À lancer
A10: S5 | B10: 46293 | C10: 46299 | D10: Fermer les lacunes géographiques | E10: Publier ou sécuriser les quatre sujets des pays sans couverture; lancer “55 pays, 55 regards”. | F10: Coordination Afrique | G10: 4 articles / commandes | H10: 55 pays couverts ou commandes fermes | I10: 4 octobre | J10: À lancer
A11: S6 | B11: 46300 | C11: 46306 | D11: Installer la programmation | E11: Appliquer la grille de rubriques; lancer conférence hebdomadaire et calendrier à quatre semaines. | F11: Conférence de rédaction | G11: Calendrier octobre | H11: 100 % des commandes affectées à une rubrique | I11: 11 octobre | J11: À lancer
A12: S7 | B12: 46307 | C12: 46313 | D12: Améliorer la distribution | E12: Généraliser packs RS/SEO, CTA, UTM et calendrier Facebook/X/WhatsApp. | F12: Audience / Réseaux sociaux | G12: Pack distribution v1 | H12: ≥ 80 % des liens balisés | I12: 18 octobre | J12: À lancer
A13: S8 | B13: 46314 | C13: 46320 | D13: Commencer l’assainissement | E13: Traiter les 50 articles les plus vus : sources, SEO, image, pays, langue et mise à jour. | F13: Éditeurs / CMS | G13: Lot 1 corrigé | H13: 50 articles remis à niveau | I13: 25 octobre | J13: À lancer
A14: S9 | B14: 46321 | C14: 46327 | D14: Renforcer le réseau | E14: Sélectionner correspondants et relecteurs; valider conditions de collaboration et délais. | F14: Direction / Coordination Afrique | G14: Vivier validé | H14: 5 correspondants et 8 experts identifiés | I14: 1er novembre | J14: À lancer
A15: S10 | B15: 46328 | C15: 46334 | D15: Mesurer le premier cycle | E15: Produire le premier tableau mensuel : pays, thèmes, auteurs, qualité, audience et conversions. | F15: Analytics / Rédaction | G15: Dashboard octobre | H15: Revue tenue avant le 8 novembre | I15: 8 novembre | J15: À lancer
A16: S11 | B16: 46335 | C16: 46341 | D16: Optimiser les formats | E16: Comparer deux cohortes de titres, horaires et canaux; formaliser les premières décisions. | F16: Audience / Édition | G16: Note de test n°1 | H16: Résultats J+7 documentés | I16: 15 novembre | J16: À lancer
... A18: S13 | B18: 46349 | C18: 46356 | D18: Clore les 90 jours | E18: Atteindre 200 articles corrigés; réaliser la revue stratégique; approuver le plan des mois 4 à 6. | F18: Comité éditorial | G18: Rapport J+90 | H18: KPI, écarts, décisions et budget documentés | I18: 30 novembre | J18: À lancer
A21: Règle de pilotage | B21: Règle de pilotage | C21: Règle de pilotage | D21: Règle de pilotage | E21: Règle de pilotage | F21: Règle de pilotage | G21: Règle de pilotage | H21: Règle de pilotage | I21: Règle de pilotage | J21: Règle de pilotage
A22: Chaque fin de semaine, le responsable met à jour le statut, joint une preuve et indique tout blocage. Les sujets P0 non terminés à l’échéance sont automatiquement inscrits à l’ordre du jour du comité éditorial. La revue J+30 vérifie les fondations; la revue J+60 mesure l’adoption; la revue J+90 décide du passage à l’échelle.

Sheet Recommandations auteurs
A1: AfricaVET — recommandations détaillées par auteur
A2: Les objectifs individuels doivent être confirmés en entretien et contextualisés par disponibilité, commande, ancienneté et format
A4: Auteur | B4: Articles | C4: 90 derniers jours | D4: Vues/article | E4: Impact moyen | F4: Rôle éditorial proposé | G4: Forces observées | H4: Risques / écarts | I4: Rubriques prioritaires | J4: Actions J+30 | K4: Objectif J+90 | L4: Objectif à 6 mois | M4: Appui nécessaire | N4: KPI individuel | O4: Disponibilité
A5: Malick Kane | B5: 798 | C5: 147 | D5: 21.911028 | E5: 48.585965 | F5: Lead de production, mentor et garant de la continuité | G5: Volume exceptionnel; couverture de 49 pays; maîtrise de nombreux sujets; forte réactivité | H5: Dépendance de la rédaction; risque de surcharge; signatures trop concentrées; contrôle qualité difficile à ce volume | I5: Alertes majeures; analyses continentales; dossiers stratégiques; mentorat | J5: Réduire les tâches mécaniques; déléguer 20 % des brèves; valider deux modèles de dossier; documenter les méthodes | K5: Mentorer deux auteurs/correspondants; faire passer chaque article par la check-list; limiter les réécritures après publication | L5: Ramener sa part sous 68 % sans réduire la qualité; piloter un dossier majeur/mois; conduire la revue mensuelle | M5: Appui édition/SEO, desk de fact-checking et correspondants régionaux | N5: Complétude ≥ 70; corrections < 5 %; 2 auteurs mentorés; impact moyen maintenu | O5: Actif — à confirmer formellement
A6: Mac Juliette Johngwe | B6: 85 | C6: 29 | D6: 24.4 | E6: 63.330588 | F6: Référence proposée pour analyses et formats à fort impact | G6: Meilleure moyenne de vues et meilleur impact moyen; activité récente élevée; potentiel bilingue | H6: Portefeuille thématique à clarifier; besoin de consolider sources, SEO et traçabilité | I6: Analyses; innovations; élevage durable; data stories; entretiens experts | J6: Définir trois séries récurrentes; sécuriser un réseau de cinq experts; standardiser les sources et jeux de données | K6: Publier 8 à 12 contenus à forte valeur; au moins deux data stories ou analyses longues; former un pair | L6: Tenir un rendez-vous analytique bimensuel; impact moyen ≥ 65; complétude ≥ 75 | M6: Accès aux données, accompagnement visualisation et relecture scientifique | N6: Impact moyen ≥ 65; 30 % de formats longs; 100 % sources tracées | O6: Active — à confirmer formellement
A7: Flora J. Ingah | B7: 87 | C7: 0 | D7: 20.206897 | E7: 51.087356 | F7: Axe anglophone et suivi institutionnel, sous réserve de réactivation | G7: Corpus solide; part anglaise importante; bonne médiane de vues; expérience des sujets institutionnels | H7: Aucune publication récente sur 90 jours; rôle et disponibilité non confirmés | I7: Actualités anglophones; politiques sanitaires; institutions; entretiens | J7: Entretien de réactivation; choisir deux rubriques; actualiser la fiche auteur et les accès | K7: Si réactivée : 4 à 6 articles, dont deux interviews ou analyses anglophones; 100 % métadonnées | L7: Si active : 2 à 4 articles/mois; contribuer à la qualité linguistique EN | M7: Briefs réguliers, planning réaliste, soutien SEO et accès aux interlocuteurs | N7: Reprise effective; 100 % champs EN corrects; vues/article ≥ médiane | O7: À confirmer avant fixation des quotas
A8: Simon Yaya | B8: 67 | C8: 0 | D8: 21 | E8: 51.950746 | F8: Couverture pays et décryptages nationaux, sous réserve de réactivation | G8: Bonne médiane; capacité à traiter l’économie de l’élevage et les enjeux pays | H8: Aucune activité récente sur 90 jours; spécialisation et zone de couverture à préciser | I8: Dossiers pays; économie et marchés; élevage; voix des acteurs | J8: Entretien; confirmer pays/régions accessibles; proposer une série de trois sujets liés | K8: Si réactivé : 3 à 5 articles nationaux avec au moins trois voix locales par reportage | L8: Si actif : deux dossiers pays/mois; contribuer à “55 pays, 55 regards” | M8: Réseau de sources locales, budget reportage et accompagnement données | N8: Nombre de pays couverts; diversité des sources; impact moyen ≥ 55 | O8: À confirmer avant fixation des quotas
A9: Absan Bibou | B9: 7 | C9: 0 | D9: 8.8571429 | E9: 17.085714 | F9: Réactivation ciblée ou statut d’archive à décider | G9: Expérience historique sur One Health et santé publique | H9: Faible volume; aucune activité récente; données anciennes insuffisantes pour fixer une cible performante | I9: One Health; archives; mémoire institutionnelle; fact-check historique | J9: Vérifier disponibilité et intérêt; décider réactivation, contributeur ponctuel ou compte archivé | K9: Si réactivé : un article pilote accompagné et une évaluation éditoriale | L9: Si concluant : un contenu spécialisé/mois; sinon maintien comme archive sans quota | M9: Mentorat, brief très cadré et relecture rapprochée | N9: Décision de statut; qualité du pilote; respect de la check-list | O9: À décider dans les 30 jours
A12: Recommandations transversales pour l’équipe | B12: Recommandations transversales pour l’équipe | C12: Recommandations transversales pour l’équipe | D12: Recommandations transversales pour l’équipe | E12: Recommandations transversales pour l’équipe | F12: Recommandations transversales pour l’équipe | G12: Recommandations transversales pour l’équipe | H12: Recommandations transversales pour l’équipe | I12: Recommandations transversales pour l’équipe | J12: Recommandations transversales pour l’équipe | K12: Recommandations transversales pour l’équipe | L12: Recommandations transversales pour l’équipe | M12: Recommandations transversales pour l’équipe | N12: Recommandations transversales pour l’équipe | O12: Recommandations transversales pour l’équipe
A13: 1. Aucun quota individuel ne doit être confirmé sans entretien sur la disponibilité, le statut contractuel et les zones de compétence. 2. Séparer les objectifs de volume, qualité, impact, diversité des sources et couverture géographique. 3. Mettre en place un binôme auteur–éditeur pour chaque sujet complexe et un référent scientifique pour les contenus sanitaires sensibles. 4. Organiser une séance mensuelle de retour d’expérience à partir de deux articles réussis et de deux articles à améliorer. 5. Protéger le temps des auteurs à fort volume en confiant la mise en forme, le SEO, l’intégration CMS et la diffusion à des fonctions dédiées. 6. Recruter progressivement des correspondants afin de réduire la concentration sans fragiliser la cadence de publication.

Sheet Rubriques éditoriales
A1: AfricaVET — stratégie des rubriques et formats journalistiques
A2: Mix éditorial recommandé, exigences minimales, fréquence et indicateurs de succès
A4: 10 | E4: 1 | I4: 8 | M4: 55
A8: Formats structurés | E8: Mix éditorial total | I8: Piliers thématiques | M8: Série panafricaine
A10: Format / rubrique | B10: Objectif journalistique | C10: Part cible | D10: Fréquence indicative | E10: Longueur | F10: Sources minimales | G10: Éléments obligatoires | H10: Niveau de validation | I10: Canaux prioritaires | J10: KPI principal
A11: Alerte sanitaire / Breaking news | B11: Informer vite sans spéculation et préciser ce qui est confirmé, probable ou inconnu | C11: 0.12 | D11: Selon l’actualité | E11: 300–500 mots | F11: 2, dont 1 primaire | G11: Date/lieu; situation; source officielle; risques; prochaines étapes; mention de mise à jour | H11: Niveau 2 ou 3 | I11: Site; WhatsApp; X; Facebook | J11: Délai de publication; corrections; vues à J+1
A12: Actualité nationale | B12: Rendre compte d’une décision, campagne, événement ou évolution pays | C12: 0.23 | D12: Quotidienne | E12: 500–800 mots | F12: 2 indépendantes | G12: Angle pays; chiffres; citation; contexte; impact pour les acteurs; lien primaire | H12: Niveau 1 ou 2 | I12: Site; Facebook; WhatsApp | J12: Couverture pays; vues à J+7
A13: Analyse / décryptage | B13: Expliquer causes, conséquences, limites et options de politique publique | C13: 0.15 | D13: 2 à 3/semaine | E13: 900–1 500 mots | F13: 3 | G13: Problème; données; voix contradictoires; limites; scénarios; conclusion utile | H13: Niveau 2 | I13: Site; newsletter; LinkedIn | J13: Temps d’engagement; citations externes
A14: Reportage terrain | B14: Faire entendre les acteurs et documenter les réalités opérationnelles | C14: 0.1 | D14: 1 à 2/semaine | E14: 800–1 200 mots | F14: 3 voix locales | G14: Observation; contexte; citations; photos créditées; données locales; limites | H14: Niveau 2 | I14: Site; Facebook; WhatsApp; vidéo | J14: Diversité des voix; portée locale
A15: Entretien / Q&A | B15: Apporter expertise, responsabilité institutionnelle ou témoignage direct | C15: 0.08 | D15: 1 à 2/semaine | E15: 700–1 200 mots | F15: 1 invité + vérifications | G15: Présentation; questions structurées; citations validées; conflits d’intérêts; liens utiles | H15: Niveau 1 ou 2 | I15: Site; newsletter; réseaux | J15: Taux de lecture; reprises
A16: Guide pratique / fiche technique | B16: Répondre à un besoin concret des vétérinaires, éleveurs ou décideurs | C16: 0.1 | D16: 1 à 2/semaine | E16: 900–1 600 mots | F16: 3, dont normes | G16: Public cible; étapes; erreurs à éviter; quand consulter; sources; avertissement sanitaire | H16: Niveau 3 | I16: Site; WhatsApp; téléchargement | J16: Téléchargements; recherche organique
A17: Data story / cartographie | B17: Transformer données et cartes en information accessible et vérifiable | C17: 0.07 | D17: 2/mois | E17: 800–1 400 mots | F17: Jeu de données + méthode | G17: Source; période; définitions; méthode; graphique; limites; fichier téléchargeable | H17: Niveau 2 | I17: Site; newsletter; LinkedIn | J17: Backlinks; téléchargements; temps
A18: Dossier thématique | B18: Réunir plusieurs angles et formats sur une priorité panafricaine | C18: 0.05 | D18: 1/mois | E18: 1 500–2 500 mots | F18: 5 | G18: Chronologie; données; pays; experts; solutions; bibliographie; mises à jour | H18: Niveau 3 | I18: Site; newsletter; partenaires | J18: Durée de vie; abonnements; citations
A19: Opportunités / appels | B19: Diffuser rapidement une information vérifiée et directement exploitable | C19: 0.05 | D19: Selon disponibilité | E19: 300–600 mots | F19: 1 source primaire | G19: Éligibilité; montant; dates; procédure; contacts; lien officiel; alerte anti-fraude | H19: Niveau 1 | I19: Site; WhatsApp; Facebook | J19: Clics sortants; conversions
A20: Fact-check / correction | B20: Corriger une information virale ou documenter une erreur importante | C20: 0.05 | D20: Selon besoin | E20: 500–1 000 mots | F20: 3, priorité aux sources primaires | G20: Affirmation; verdict; preuves; méthode; correction; date; transparence | H20: Niveau 3 ou 4 | I20: Site; X; Facebook; WhatsApp | J20: Délai de correction; reprises fiables
A24: Rééquilibrage des piliers thématiques | B24: Rééquilibrage des piliers thématiques | C24: Rééquilibrage des piliers thématiques | D24: Rééquilibrage des piliers thématiques | E24: Rééquilibrage des piliers thématiques | F24: Rééquilibrage des piliers thématiques | G24: Rééquilibrage des piliers thématiques | H24: Rééquilibrage des piliers thématiques
A25: Pilier | B25: Articles actuels | C25: Part actuelle | D25: Cible 6 mois | E25: Cible 12 mois | F25: Rythme minimum | G25: Angle à renforcer | H25: Responsable proposé
A26: Actualités et analyses transversales | B26: 315 | C26: 0.30172414 | D26: 0.27 | E26: 0.25 | F26: À plafonner | G26: Reclasser les sujets trop génériques vers un pilier précis | H26: Rédaction en chef
A27: One Health, zoonoses et santé publique | B27: 224 | C27: 0.21455939 | D27: 0.18 | E27: 0.17 | F27: 3–4/mois | G27: Prévention, systèmes, communautés, économie de la santé | H27: Référent One Health
A28: Santé animale et maladies | B28: 139 | C28: 0.13314176 | D28: 0.17 | E28: 0.17 | F28: 3–4/mois | G28: Surveillance, diagnostic, vaccination, biosécurité | H28: Référent scientifique
A29: Élevage et productions animales | B29: 104 | C29: 0.099616858 | D29: 0.14 | E29: 0.14 | F29: 3/mois | G29: Productivité, bien-être, marchés, climat et pratiques | H29: Desk élevage
A30: Pêches et aquaculture | B30: 107 | C30: 0.10249042 | D30: 0.11 | E30: 0.11 | F30: 2–3/mois | G30: Santé aquatique, chaînes de valeur, pêche artisanale | H30: Desk aquatique
A31: Profession et services vétérinaires | B31: 73 | C31: 0.069923372 | D31: 0.09 | E31: 0.1 | F31: 2–3/mois | G31: Métiers, paraprofessionnels, réglementation, formation | H31: Desk profession
A32: Ressources, recherche et opportunités | B32: 67 | C32: 0.064176245 | D32: 0.07 | E32: 0.08 | F32: 2/mois | G32: Appels, outils, science africaine, transfert de connaissances | H32: Desk ressources
A33: Faune et conservation | B33: 15 | C33: 0.014367816 | D33: 0.07 | E33: 0.08 | F33: 2/mois | G33: Interfaces faune-bétail, coexistence, conservation et risques | H33: Correspondant faune
A36: Séries transversales recommandées | B36: Séries transversales recommandées | C36: Séries transversales recommandées | D36: Séries transversales recommandées | E36: Séries transversales recommandées | F36: Séries transversales recommandées | G36: Séries transversales recommandées | H36: Séries transversales recommandées | I36: Séries transversales recommandées | J36: Séries transversales recommandées | K36: Séries transversales recommandées | L36: Séries transversales recommandées | M36: Séries transversales recommandées | N36: Séries transversales recommandées | O36: Séries transversales recommandées | P36: Séries transversales recommandées | Q36: Séries transversales recommandées | R36: Séries transversales recommandées
A37: Série | B37: Promesse | C37: Fréquence | D37: Format dominant | E37: Objectif 6 mois | F37: KPI
A38: 55 pays, 55 regards | B38: Donner une place régulière à chaque État membre de l’UA | C38: 1/semaine | D38: Reportage ou dossier pays | E38: 18 pays publiés | F38: Pays couverts; sources locales
A39: Alerte santé animale | B39: Séparer faits confirmés, incertitudes et conseils opérationnels | C39: Selon besoin | D39: Alerte + mise à jour | E39: Protocole utilisé à 100 % | F39: Délai; corrections
A40: Métiers vétérinaires | B40: Valoriser vétérinaires, paraprofessionnels, laboratoires et services | C40: 1/semaine | D40: Portrait / entretien | E40: 24 professionnels | F40: Diversité pays et genre
A41: Data AfricaVET | B41: Expliquer une tendance par les données | C41: 2/mois | D41: Data story | E41: 12 analyses | F41: Backlinks; téléchargements
A42: Voix du terrain | B42: Faire entendre éleveurs, pêcheurs, communautés et agents locaux | C42: 1/semaine | D42: Reportage | E42: 24 sujets | F42: Nombre et diversité des voix
A43: Le point scientifique | B43: Traduire une publication ou norme en décision pratique | C43: 2/mois | D43: Analyse / guide | E43: 12 synthèses | F43: Temps de lecture; citations

Sheet Standards et workflow
A1: AfricaVET — standards journalistiques et workflow de publication
A2: Délais, responsabilités, preuves obligatoires, critères de blocage et protocole de correction
A4: Workflow éditorial standard | B4: Workflow éditorial standard | C4: Workflow éditorial standard | D4: Workflow éditorial standard | E4: Workflow éditorial standard | F4: Workflow éditorial standard | G4: Workflow éditorial standard | H4: Workflow éditorial standard | J4: Niveaux de validation | K4: Niveaux de validation | L4: Niveaux de validation | M4: Niveaux de validation | N4: Niveaux de validation
A5: Étape | B5: SLA indicatif | C5: Responsable (R) | D5: Approbateur (A) | E5: Consultés (C) | F5: Preuve obligatoire | G5: Critère Go / No-Go | H5: Action si échec | J5: Niveau | K5: Usage | L5: Validation minimale | M5: Délai cible | N5: Exemples
A6: 1. Proposition / commande | B6: ≤ 4 h actualité; 48 h dossier | C6: Auteur / Desk | D6: Rédaction en chef | E6: Coordination régionale | F6: Pitch avec angle, public, format et échéance | G6: Angle distinct et utile; absence de doublon | H6: Reformuler ou abandonner | J6: N1 — courant | K6: Information factuelle à faible risque | L6: Auteur + éditeur | M6: Même jour | N6: Opportunité; annonce; compte rendu
A7: 2. Pré-vérification | B7: Avant rédaction | C7: Auteur | D7: Éditeur | E7: Référent scientifique | F7: Liste initiale des sources et risques | G7: Au moins une source primaire accessible | H7: Suspendre et rechercher | J7: N2 — technique | K7: Sujet vétérinaire ou politique nécessitant contexte | L7: Auteur + éditeur + référent | M7: ≤ 24 h | N7: Campagne; réglementation; analyse
A8: 3. Collecte / entretiens | B8: Selon format | C8: Auteur | D8: Éditeur | E8: Experts / acteurs locaux | F8: Notes, enregistrements autorisés, documents et données | G8: Sources identifiées; citations vérifiables | H8: Compléter le reportage | J8: N3 — sensible | K8: Alerte maladie, santé publique, médicament ou conseil | L8: Double vérification + direction | M8: Avant diffusion | N8: Foyer; zoonose; diagnostic; guide
A9: 4. Rédaction | B9: 2 h à 7 jours | C9: Auteur | D9: Éditeur | E9: Référent thématique | F9: Version datée et liens sources | G9: Structure, angle, chiffres et contexte complets | H9: Retour auteur | J9: N4 — juridique / enquête | K9: Accusation, conflit, données personnelles ou investigation | L9: Direction + avis juridique | M9: Selon risque | N9: Fraude; responsabilité; droit de réponse
A10: 5. Relecture scientifique | B10: ≤ 4 h alerte; 24 h analyse | C10: Référent scientifique | D10: Rédaction en chef | E10: Laboratoire / institution | F10: Avis tracé dans le CMS | G10: Aucune erreur sanitaire majeure; incertitudes explicites | H10: Bloquer publication
A11: 6. Édition journalistique | B11: ≤ 4 h | C11: Éditeur | D11: Rédaction en chef | E11: Auteur | F11: Version révisée; titres et citations contrôlés | G11: Clarté, équilibre, attribution et conformité éthique | H11: Retour auteur / arbitrage
A12: 7. SEO et intégration CMS | B12: ≤ 1 h | C12: Webmaster / SEO | D12: Éditeur | E12: Auteur | F12: Tous champs obligatoires et aperçu social | G12: Score de complétude prépublication ≥ 80/100 | H12: Publication bloquée | J12: Protocole de correction | K12: Protocole de correction | L12: Protocole de correction | M12: Protocole de correction | N12: Protocole de correction
A13: 8. Validation finale | B13: ≤ 30 min | C13: Rédaction en chef | D13: Direction si sensible | E13: Juridique / partenaire | F13: Bon à publier horodaté | G13: Risque juridique et scientifique acceptable | H13: Escalade ou report | J13: 1. Corriger immédiatement l’erreur factuelle sans effacer l’historique. 2. Ajouter une note datée précisant ce qui a changé et pourquoi. 3. Informer les canaux sociaux si l’erreur a été diffusée largement. 4. Alerter les personnes ou institutions directement concernées. 5. En cas d’erreur majeure, revoir la cause, le workflow et la formation nécessaire.
A14: 9. Publication / diffusion | B14: Immédiat | C14: Webmaster + Réseaux sociaux | D14: Éditeur | E14: Auteur | F14: URL, UTM, pack Facebook/X/WhatsApp | G14: Liens, visuels et appels à l’action fonctionnels | H14: Corriger avant diffusion
A15: 10. Suivi / mise à jour | B15: J+1, J+7, J+30 | C15: Audience + Auteur | D15: Éditeur | E15: Référent scientifique | F15: Vues, engagement, corrections et mises à jour | G15: Évolution importante intégrée; erreurs corrigées | H15: Ajouter note de mise à jour
A18: Check-list obligatoire avant publication | B18: Check-list obligatoire avant publication | C18: Check-list obligatoire avant publication | D18: Check-list obligatoire avant publication | E18: Check-list obligatoire avant publication | F18: Check-list obligatoire avant publication | G18: Check-list obligatoire avant publication | H18: Check-list obligatoire avant publication
A19: N° | B19: Contrôle | C19: Pourquoi | D19: Preuve dans le CMS | E19: Bloquant | F19: Responsable | G19: Quand
A20: 1 | B20: Angle et public cible explicites | C20: Éviter les contenus génériques | D20: Champ angle / brief | E20: Oui | F20: Éditeur | G20: Commande
A21: 2 | B21: Au moins deux sources; une primaire | C21: Réduire erreur et dépendance | D21: Liens et noms des sources | E21: Oui | F21: Auteur | G21: Avant rédaction
A22: 3 | B22: Chiffres, dates et unités vérifiés | C22: Éviter erreurs factuelles | D22: Document ou jeu de données | E22: Oui | F22: Auteur / Éditeur | G22: Relecture
A23: 4 | B23: Citation attribuée et fidèle | C23: Protéger les personnes et la crédibilité | D23: Notes ou validation | E23: Oui | F23: Auteur | G23: Relecture
A24: 5 | B24: Pays, région et portée renseignés | C24: Permettre le pilotage des 55 pays | D24: Champs CMS | E24: Oui | F24: Webmaster | G24: Intégration
A25: 6 | B25: Langue d’origine réelle renseignée | C25: Fiabiliser la publication bilingue | D25: Champ langue | E25: Oui | F25: Webmaster | G25: Intégration
A26: 7 | B26: Catégorie, macrothème et format corrects | C26: Éviter la rubrique générique | D26: Taxonomie CMS | E26: Oui | F26: Éditeur | G26: Intégration
A27: 8 | B27: Image autorisée, créditée et légendée | C27: Respecter droits et traçabilité | D27: Crédit, source, légende | E27: Oui | F27: Webmaster | G27: Intégration
A28: 9 | B28: Conflits d’intérêts et partenariat déclarés | C28: Préserver l’indépendance | D28: Mention publique si applicable | E28: Oui si applicable | F28: Éditeur | G28: Validation
A29: 10 | B29: Avertissement sanitaire présent | C29: Limiter les conseils dangereux | D29: Bloc disclaimer | E29: Oui si applicable | F29: Référent scientifique | G29: Validation
A30: 11 | B30: Méta-titre 50–60 caractères | C30: Améliorer affichage et recherche | D30: Champ SEO | E30: Oui | F30: SEO | G30: Intégration
A31: 12 | B31: Méta-description 140–160 caractères | C31: Clarifier la promesse de lecture | D31: Champ SEO | E31: Oui | F31: SEO | G31: Intégration
... A35: 16 | B35: Heure, auteur et validation tracés | C35: Assurer responsabilité et audit | D35: Journal CMS | E35: Oui | F35: Rédaction en chef | G35: Publication

Sheet KPI et gouvernance
A1: AfricaVET — KPI, cibles et gouvernance éditoriale
A2: Valeurs de référence au 25 août 2026 | Les cellules jaunes “Réalisé actuel” sont à mettre à jour lors de chaque revue
A4: 51 | E4: 21.829502 | I4: 0.76436782 | M4: 2
A8: Pays couverts | E8: Complétude moyenne | I8: Part du premier auteur | M8: Auteurs actifs sur 90 jours
A10: ID | B10: KPI | C10: Sens | D10: Référence | E10: Unité | F10: Cible J+30 | G10: Cible J+90 | H10: Cible 6 mois | I10: Cible 12 mois | J10: Réalisé actuel | K10: Écart vs J+90 | L10: Responsable | M10: Source | N10: Fréquence
A11: 1 | B11: Pays UA couverts | C11: Hausse | D11: 51 | E11: pays | F11: 55 | G11: 55 | H11: 55 | I11: 55 | J11: 51 | K11: =IF(C11="Hausse",J11-G11,G11-J11) -> -4 | L11: Coordination Afrique | M11: Classement 55 | N11: Mensuelle
A12: 2 | B12: Pays UA sans article national | C12: Baisse | D12: 4 | E12: pays | F12: 0 | G12: 0 | H12: 0 | I12: 0 | J12: 4 | K12: =IF(C12="Hausse",J12-G12,G12-J12) -> -4 | L12: Coordination Afrique | M12: Classement 55 | N12: Mensuelle
A13: 3 | B13: Part du premier auteur | C13: Baisse | D13: 0.76436782 | E13: % | F13: 0.74 | G13: 0.72 | H13: 0.68 | I13: 0.6 | J13: 0.76436782 | K13: =IF(C13="Hausse",J13-G13,G13-J13) -> -0.044367816 | L13: Rédaction en chef | M13: Auteurs | N13: Mensuelle
A14: 4 | B14: Auteurs actifs sur 90 jours | C14: Hausse | D14: 2 | E14: auteurs | F14: 3 | G14: 4 | H14: 6 | I14: 8 | J14: 2 | K14: =IF(C14="Hausse",J14-G14,G14-J14) -> -2 | L14: Rédaction en chef | M14: Auteurs | N14: Mensuelle
A15: 5 | B15: Score moyen de complétude | C15: Hausse | D15: 21.829502 | E15: /100 | F15: 35 | G15: 50 | H15: 70 | I15: 85 | J15: 21.829502 | K15: =IF(C15="Hausse",J15-G15,G15-J15) -> -28.170498 | L15: Qualité / CMS | M15: Qualité éditoriale | N15: Mensuelle
A16: 6 | B16: Champ pays renseigné dans le corpus | C16: Hausse | D16: 0.058429119 | E16: % | F16: 0.15 | G16: 0.25 | H16: 0.6 | I16: 0.95 | J16: 0.058429119 | K16: =IF(C16="Hausse",J16-G16,G16-J16) -> -0.19157088 | L16: Webmaster | M16: Corpus / API | N16: Mensuelle
A17: 7 | B17: Méta-titre renseigné | C17: Hausse | D17: 0.08908046 | E17: % | F17: 0.2 | G17: 0.35 | H17: 0.65 | I17: 0.95 | J17: 0.08908046 | K17: =IF(C17="Hausse",J17-G17,G17-J17) -> -0.26091954 | L17: SEO / CMS | M17: Qualité éditoriale | N17: Mensuelle
A18: 8 | B18: Méta-description renseignée | C18: Hausse | D18: 0.099616858 | E18: % | F18: 0.2 | G18: 0.35 | H18: 0.65 | I18: 0.95 | J18: 0.099616858 | K18: =IF(C18="Hausse",J18-G18,G18-J18) -> -0.25038314 | L18: SEO / CMS | M18: Qualité éditoriale | N18: Mensuelle
A19: 9 | B19: Crédit ou source image renseigné | C19: Hausse | D19: 0.0019157088 | E19: % | F19: 0.1 | G19: 0.25 | H19: 0.6 | I19: 0.95 | J19: 0.0019157088 | K19: =IF(C19="Hausse",J19-G19,G19-J19) -> -0.24808429 | L19: Webmaster | M19: Qualité éditoriale | N19: Mensuelle
A20: 10 | B20: Sources structurées renseignées | C20: Hausse | D20: 0 | E20: % | F20: 0.1 | G20: 0.25 | H20: 0.6 | I20: 0.95 | J20: 0 | K20: =IF(C20="Hausse",J20-G20,G20-J20) -> -0.25 | L20: Auteurs / Éditeurs | M20: Qualité éditoriale | N20: Mensuelle
A21: 11 | B21: Relecture ou vérification tracée | C21: Hausse | D21: 0 | E21: % | F21: 0.1 | G21: 0.25 | H21: 0.6 | I21: 0.95 | J21: 0 | K21: =IF(C21="Hausse",J21-G21,G21-J21) -> -0.25 | L21: Rédaction en chef | M21: Qualité éditoriale | N21: Mensuelle
A22: 12 | B22: Incohérences de langue FR/EN | C22: Baisse | D22: 385 | E22: articles | F22: 200 | G22: 0 | H22: 0 | I22: 0 | J22: 385 | K22: =IF(C22="Hausse",J22-G22,G22-J22) -> -385 | L22: Webmaster / Langues | M22: API / Corpus | N22: Hebdomadaire jusqu’à zéro
... A30: 20 | B30: Articles de la série 55 pays, 55 regards | C30: Hausse | D30: 0 | E30: articles | F30: 4 | G30: 12 | H30: 30 | I30: 55 | J30: 0 | K30: =IF(C30="Hausse",J30-G30,G30-J30) -> -12 | L30: Coordination Afrique | M30: Calendrier éditorial | N30: Mensuelle
A33: Instances et cadence de gouvernance | B33: Instances et cadence de gouvernance | C33: Instances et cadence de gouvernance | D33: Instances et cadence de gouvernance | E33: Instances et cadence de gouvernance | F33: Instances et cadence de gouvernance | G33: Instances et cadence de gouvernance | H33: Instances et cadence de gouvernance | I33: Instances et cadence de gouvernance | J33: Instances et cadence de gouvernance | K33: Instances et cadence de gouvernance | L33: Instances et cadence de gouvernance | M33: Instances et cadence de gouvernance | N33: Instances et cadence de gouvernance
A34: Instance | C34: Composition minimale | F34: Cadence | H34: Décisions attendues | J34: Entrées | M34: Sorties
A35: Desk quotidien | C35: Éditeur de permanence; auteur; réseaux sociaux | F35: 15 min chaque matin | H35: Priorités du jour; alertes; mises à jour | J35: Agenda, veille, incidents | M35: Liste de commandes et responsables
A36: Conférence hebdomadaire | C36: Rédaction en chef; auteurs; audience; CMS | F36: 1 fois/semaine | H36: Calendrier à 4 semaines; formats; pays; sources | J36: Pitchs, KPI courts, calendrier | M36: Commandes et arbitrages
A37: Revue audience et qualité | C37: Audience; SEO; CMS; éditeur | F37: 1 fois/semaine | H37: Corrections rapides; distribution; tests | J37: Top/bottom articles; UTM; erreurs | M37: Actions correctives
A38: Comité éditorial mensuel | C38: Direction; rédaction; scientifique; audience | F38: Avant le 7 du mois | H38: Ressources; écarts KPI; risques; partenariats | J38: Dashboard complet; corrections; plaintes | M38: Compte rendu et plan du mois
A39: Revue stratégique trimestrielle | C39: Direction; comité; partenaires invités si utile | F39: Trimestrielle | H39: Rééquilibrage pays/thèmes; réseau; budget | J39: Tendances 3 mois; audit échantillon | M39: Décisions stratégiques
A40: Rapport annuel | C40: Direction et rédaction | F40: Annuelle | H40: Priorités, ressources, indépendance et impact | J40: Données annuelles consolidées | M40: Rapport public et plan annuel
A43: RACI simplifié | B43: RACI simplifié | C43: RACI simplifié | D43: RACI simplifié | E43: RACI simplifié | F43: RACI simplifié | G43: RACI simplifié | H43: RACI simplifié | I43: RACI simplifié | J43: RACI simplifié | K43: RACI simplifié | L43: RACI simplifié | M43: RACI simplifié | N43: RACI simplifié
A44: Activité | C44: Direction | E44: Rédaction en chef | G44: Auteur | I44: Référent scientifique | K44: CMS / SEO | M44: Audience
A45: Stratégie annuelle | C45: A | E45: R | G45: C | I45: C | K45: C | M45: C
A46: Commande éditoriale | C46: I | E46: A/R | G46: C | I46: C | K46: I | M46: I
A47: Collecte et rédaction | C47: I | E47: A | G47: R | I47: C | K47: I | M47: I
A48: Validation scientifique | C48: I | E48: A | G48: C | I48: R | K48: I | M48: I
A49: SEO et intégration | C49: I | E49: A | G49: C | I49: C | K49: R | M49: C
A50: Publication et correction | C50: I | E50: A/R | G50: C | I50: C | K50: R | M50: C
A51: Diffusion et conversion | C51: I | E51: A | G51: C | I51: I | K51: C | M51: R
A52: Revue des KPI | C52: A | E52: R | G52: C | I52: C | K52: C | M52: R
A55: Légende RACI et règle d’escalade | B55: Légende RACI et règle d’escalade | C55: Légende RACI et règle d’escalade | D55: Légende RACI et règle d’escalade | E55: Légende RACI et règle d’escalade | F55: Légende RACI et règle d’escalade | G55: Légende RACI et règle d’escalade | H55: Légende RACI et règle d’escalade | I55: Légende RACI et règle d’escalade | J55: Légende RACI et règle d’escalade | K55: Légende RACI et règle d’escalade | L55: Légende RACI et règle d’escalade | M55: Légende RACI et règle d’escalade | N55: Légende RACI et règle d’escalade
A56: R = réalise; A = approuve et répond du résultat; C = consulté; I = informé. Une activité critique ne doit avoir qu’un seul A. Tout contenu de niveau 3 ou 4 est automatiquement escaladé à la rédaction en chef; la direction intervient si le risque juridique, institutionnel ou réputationnel est significatif.

Sheet Classement 55
A1: AfricaVET — classement éditorial des 55 États membres de l’UA
A2: Corpus au 25 août 2026 | Les comptes nationaux sont distincts des articles régionaux, continentaux et multinationaux
A4: Rang | B4: Pays | C4: Région UA | D4: Articles nationaux | E4: Confirmés | F4: Contextuels | G4: Mentions totales | H4: Part nationale | I4: Articles 2026 | J4: 12 derniers mois | K4: Première publication | L4: Dernière publication | M4: Jours sans article | N4: Niveau de couverture | O4: Priorité éditoriale | P4: Thème dominant | Q4: Diversité thématique | R4: Vues cumulées | S4: Attr. élevée | T4: Attr. moyenne
A5: 1 | B5: Cameroun | C5: Afrique centrale | D5: =COUNTIFS(Corpus!$F$2:$F$1045,B5,Corpus!$I$2:$I$1045,"National") -> 112 | E5: =COUNTIFS(Corpus!$F$2:$F$1045,B5,Corpus!$I$2:$I$1045,"National",Corpus!$J$2:$J$1045,"<>Début du texte") -> 105 | F5: =COUNTIFS(Corpus!$F$2:$F$1045,B5,Corpus!$I$2:$I$1045,"National",Corpus!$J$2:$J$1045,"Début du texte") -> 7 | G5: 123 | H5: =IFERROR(D5/SUM($D$5:$D$59),0) -> 0.20326679 | I5: =COUNTIFS(Corpus!$F$2:$F$1045,B5,Corpus!$I$2:$I$1045,"National",Corpus!$C$2:$C$1045,2026) -> 19 | J5: =COUNTIFS(Corpus!$F$2:$F$1045,B5,Corpus!$I$2:$I$1045,"National",Corpus!$B$2:$B$1045,">="&DATE(2025,8,26)) -> 29 | K5: 43918 | L5: 46259 | M5: 0 | N5: Très élevée | O5: P4 - maintenir/diversifier | P5: One Health, zoonoses et santé publique | Q5: 8 | R5: =SUMIFS(Corpus!$O$2:$O$1045,Corpus!$F$2:$F$1045,B5,Corpus!$I$2:$I$1045,"National") -> 2309 | S5: 104 | T5: 8
A6: 2 | B6: Sénégal | C6: Afrique de l'Ouest | D6: =COUNTIFS(Corpus!$F$2:$F$1045,B6,Corpus!$I$2:$I$1045,"National") -> 74 | E6: =COUNTIFS(Corpus!$F$2:$F$1045,B6,Corpus!$I$2:$I$1045,"National",Corpus!$J$2:$J$1045,"<>Début du texte") -> 72 | F6: =COUNTIFS(Corpus!$F$2:$F$1045,B6,Corpus!$I$2:$I$1045,"National",Corpus!$J$2:$J$1045,"Début du texte") -> 2 | G6: 93 | H6: =IFERROR(D6/SUM($D$5:$D$59),0) -> 0.13430127 | I6: =COUNTIFS(Corpus!$F$2:$F$1045,B6,Corpus!$I$2:$I$1045,"National",Corpus!$C$2:$C$1045,2026) -> 17 | J6: =COUNTIFS(Corpus!$F$2:$F$1045,B6,Corpus!$I$2:$I$1045,"National",Corpus!$B$2:$B$1045,">="&DATE(2025,8,26)) -> 22 | K6: 44647 | L6: 46259 | M6: 0 | N6: Très élevée | O6: P4 - maintenir/diversifier | P6: Actualités et analyses transversales | Q6: 7 | R6: =SUMIFS(Corpus!$O$2:$O$1045,Corpus!$F$2:$F$1045,B6,Corpus!$I$2:$I$1045,"National") -> 1279 | S6: 72 | T6: 2
A7: 3 | B7: Côte d’Ivoire | C7: Afrique de l'Ouest | D7: =COUNTIFS(Corpus!$F$2:$F$1045,B7,Corpus!$I$2:$I$1045,"National") -> 46 | E7: =COUNTIFS(Corpus!$F$2:$F$1045,B7,Corpus!$I$2:$I$1045,"National",Corpus!$J$2:$J$1045,"<>Début du texte") -> 43 | F7: =COUNTIFS(Corpus!$F$2:$F$1045,B7,Corpus!$I$2:$I$1045,"National",Corpus!$J$2:$J$1045,"Début du texte") -> 3 | G7: 51 | H7: =IFERROR(D7/SUM($D$5:$D$59),0) -> 0.083484574 | I7: =COUNTIFS(Corpus!$F$2:$F$1045,B7,Corpus!$I$2:$I$1045,"National",Corpus!$C$2:$C$1045,2026) -> 5 | J7: =COUNTIFS(Corpus!$F$2:$F$1045,B7,Corpus!$I$2:$I$1045,"National",Corpus!$B$2:$B$1045,">="&DATE(2025,8,26)) -> 8 | K7: 44645 | L7: 46245 | M7: 14 | N7: Très élevée | O7: P4 - maintenir/diversifier | P7: Pêches et aquaculture | Q7: 7 | R7: =SUMIFS(Corpus!$O$2:$O$1045,Corpus!$F$2:$F$1045,B7,Corpus!$I$2:$I$1045,"National") -> 713 | S7: 43 | T7: 3
A8: 4 | B8: Kenya | C8: Afrique de l'Est | D8: =COUNTIFS(Corpus!$F$2:$F$1045,B8,Corpus!$I$2:$I$1045,"National") -> 39 | E8: =COUNTIFS(Corpus!$F$2:$F$1045,B8,Corpus!$I$2:$I$1045,"National",Corpus!$J$2:$J$1045,"<>Début du texte") -> 32 | F8: =COUNTIFS(Corpus!$F$2:$F$1045,B8,Corpus!$I$2:$I$1045,"National",Corpus!$J$2:$J$1045,"Début du texte") -> 7 | G8: 59 | H8: =IFERROR(D8/SUM($D$5:$D$59),0) -> 0.070780399 | I8: =COUNTIFS(Corpus!$F$2:$F$1045,B8,Corpus!$I$2:$I$1045,"National",Corpus!$C$2:$C$1045,2026) -> 15 | J8: =COUNTIFS(Corpus!$F$2:$F$1045,B8,Corpus!$I$2:$I$1045,"National",Corpus!$B$2:$B$1045,">="&DATE(2025,8,26)) -> 19 | K8: 44642 | L8: 46259 | M8: 0 | N8: Très élevée | O8: P4 - maintenir/diversifier | P8: Actualités et analyses transversales | Q8: 8 | R8: =SUMIFS(Corpus!$O$2:$O$1045,Corpus!$F$2:$F$1045,B8,Corpus!$I$2:$I$1045,"National") -> 913 | S8: 32 | T8: 7
A9: 5 | B9: Burkina Faso | C9: Afrique de l'Ouest | D9: =COUNTIFS(Corpus!$F$2:$F$1045,B9,Corpus!$I$2:$I$1045,"National") -> 24 | E9: =COUNTIFS(Corpus!$F$2:$F$1045,B9,Corpus!$I$2:$I$1045,"National",Corpus!$J$2:$J$1045,"<>Début du texte") -> 21 | F9: =COUNTIFS(Corpus!$F$2:$F$1045,B9,Corpus!$I$2:$I$1045,"National",Corpus!$J$2:$J$1045,"Début du texte") -> 3 | G9: 27 | H9: =IFERROR(D9/SUM($D$5:$D$59),0) -> 0.043557169 | I9: =COUNTIFS(Corpus!$F$2:$F$1045,B9,Corpus!$I$2:$I$1045,"National",Corpus!$C$2:$C$1045,2026) -> 11 | J9: =COUNTIFS(Corpus!$F$2:$F$1045,B9,Corpus!$I$2:$I$1045,"National",Corpus!$B$2:$B$1045,">="&DATE(2025,8,26)) -> 15 | K9: 43707 | L9: 46257 | M9: 2 | N9: Élevée | O9: P4 - maintenir/diversifier | P9: Santé animale et maladies | Q9: 5 | R9: =SUMIFS(Corpus!$O$2:$O$1045,Corpus!$F$2:$F$1045,B9,Corpus!$I$2:$I$1045,"National") -> 692 | S9: 21 | T9: 3
A10: 6 | B10: Afrique du Sud | C10: Afrique australe | D10: =COUNTIFS(Corpus!$F$2:$F$1045,B10,Corpus!$I$2:$I$1045,"National") -> 23 | E10: =COUNTIFS(Corpus!$F$2:$F$1045,B10,Corpus!$I$2:$I$1045,"National",Corpus!$J$2:$J$1045,"<>Début du texte") -> 21 | F10: =COUNTIFS(Corpus!$F$2:$F$1045,B10,Corpus!$I$2:$I$1045,"National",Corpus!$J$2:$J$1045,"Début du texte") -> 2 | G10: 35 | H10: =IFERROR(D10/SUM($D$5:$D$59),0) -> 0.041742287 | I10: =COUNTIFS(Corpus!$F$2:$F$1045,B10,Corpus!$I$2:$I$1045,"National",Corpus!$C$2:$C$1045,2026) -> 14 | J10: =COUNTIFS(Corpus!$F$2:$F$1045,B10,Corpus!$I$2:$I$1045,"National",Corpus!$B$2:$B$1045,">="&DATE(2025,8,26)) -> 16 | K10: 44515 | L10: 46255 | M10: 4 | N10: Élevée | O10: P4 - maintenir/diversifier | P10: Santé animale et maladies | Q10: 8 | R10: =SUMIFS(Corpus!$O$2:$O$1045,Corpus!$F$2:$F$1045,B10,Corpus!$I$2:$I$1045,"National") -> 596 | S10: 19 | T10: 4
A11: 7 | B11: Nigeria | C11: Afrique de l'Ouest | D11: =COUNTIFS(Corpus!$F$2:$F$1045,B11,Corpus!$I$2:$I$1045,"National") -> 23 | E11: =COUNTIFS(Corpus!$F$2:$F$1045,B11,Corpus!$I$2:$I$1045,"National",Corpus!$J$2:$J$1045,"<>Début du texte") -> 20 | F11: =COUNTIFS(Corpus!$F$2:$F$1045,B11,Corpus!$I$2:$I$1045,"National",Corpus!$J$2:$J$1045,"Début du texte") -> 3 | G11: 30 | H11: =IFERROR(D11/SUM($D$5:$D$59),0) -> 0.041742287 | I11: =COUNTIFS(Corpus!$F$2:$F$1045,B11,Corpus!$I$2:$I$1045,"National",Corpus!$C$2:$C$1045,2026) -> 6 | J11: =COUNTIFS(Corpus!$F$2:$F$1045,B11,Corpus!$I$2:$I$1045,"National",Corpus!$B$2:$B$1045,">="&DATE(2025,8,26)) -> 9 | K11: 44708 | L11: 46258 | M11: 1 | N11: Élevée | O11: P4 - maintenir/diversifier | P11: Actualités et analyses transversales | Q11: 7 | R11: =SUMIFS(Corpus!$O$2:$O$1045,Corpus!$F$2:$F$1045,B11,Corpus!$I$2:$I$1045,"National") -> 480 | S11: 20 | T11: 3
A12: 8 | B12: Tchad | C12: Afrique centrale | D12: =COUNTIFS(Corpus!$F$2:$F$1045,B12,Corpus!$I$2:$I$1045,"National") -> 20 | E12: =COUNTIFS(Corpus!$F$2:$F$1045,B12,Corpus!$I$2:$I$1045,"National",Corpus!$J$2:$J$1045,"<>Début du texte") -> 19 | F12: =COUNTIFS(Corpus!$F$2:$F$1045,B12,Corpus!$I$2:$I$1045,"National",Corpus!$J$2:$J$1045,"Début du texte") -> 1 | G12: 26 | H12: =IFERROR(D12/SUM($D$5:$D$59),0) -> 0.036297641 | I12: =COUNTIFS(Corpus!$F$2:$F$1045,B12,Corpus!$I$2:$I$1045,"National",Corpus!$C$2:$C$1045,2026) -> 7 | J12: =COUNTIFS(Corpus!$F$2:$F$1045,B12,Corpus!$I$2:$I$1045,"National",Corpus!$B$2:$B$1045,">="&DATE(2025,8,26)) -> 11 | K12: 44939 | L12: 46259 | M12: 0 | N12: Élevée | O12: P4 - maintenir/diversifier | P12: Actualités et analyses transversales | Q12: 4 | R12: =SUMIFS(Corpus!$O$2:$O$1045,Corpus!$F$2:$F$1045,B12,Corpus!$I$2:$I$1045,"National") -> 486 | S12: 19 | T12: 1
A13: 9 | B13: RDC | C13: Afrique centrale | D13: =COUNTIFS(Corpus!$F$2:$F$1045,B13,Corpus!$I$2:$I$1045,"National") -> 16 | E13: =COUNTIFS(Corpus!$F$2:$F$1045,B13,Corpus!$I$2:$I$1045,"National",Corpus!$J$2:$J$1045,"<>Début du texte") -> 11 | F13: =COUNTIFS(Corpus!$F$2:$F$1045,B13,Corpus!$I$2:$I$1045,"National",Corpus!$J$2:$J$1045,"Début du texte") -> 5 | G13: 27 | H13: =IFERROR(D13/SUM($D$5:$D$59),0) -> 0.029038113 | I13: =COUNTIFS(Corpus!$F$2:$F$1045,B13,Corpus!$I$2:$I$1045,"National",Corpus!$C$2:$C$1045,2026) -> 4 | J13: =COUNTIFS(Corpus!$F$2:$F$1045,B13,Corpus!$I$2:$I$1045,"National",Corpus!$B$2:$B$1045,">="&DATE(2025,8,26)) -> 4 | K13: 44082 | L13: 46245 | M13: 14 | N13: Élevée | O13: P4 - maintenir/diversifier | P13: Actualités et analyses transversales | Q13: 4 | R13: =SUMIFS(Corpus!$O$2:$O$1045,Corpus!$F$2:$F$1045,B13,Corpus!$I$2:$I$1045,"National") -> 314 | S13: 11 | T13: 5
A14: 10 | B14: Maroc | C14: Afrique du Nord | D14: =COUNTIFS(Corpus!$F$2:$F$1045,B14,Corpus!$I$2:$I$1045,"National") -> 15 | E14: =COUNTIFS(Corpus!$F$2:$F$1045,B14,Corpus!$I$2:$I$1045,"National",Corpus!$J$2:$J$1045,"<>Début du texte") -> 14 | F14: =COUNTIFS(Corpus!$F$2:$F$1045,B14,Corpus!$I$2:$I$1045,"National",Corpus!$J$2:$J$1045,"Début du texte") -> 1 | G14: 21 | H14: =IFERROR(D14/SUM($D$5:$D$59),0) -> 0.02722323 | I14: =COUNTIFS(Corpus!$F$2:$F$1045,B14,Corpus!$I$2:$I$1045,"National",Corpus!$C$2:$C$1045,2026) -> 7 | J14: =COUNTIFS(Corpus!$F$2:$F$1045,B14,Corpus!$I$2:$I$1045,"National",Corpus!$B$2:$B$1045,">="&DATE(2025,8,26)) -> 8 | K14: 44686 | L14: 46258 | M14: 1 | N14: Élevée | O14: P4 - maintenir/diversifier | P14: Élevage et productions animales | Q14: 6 | R14: =SUMIFS(Corpus!$O$2:$O$1045,Corpus!$F$2:$F$1045,B14,Corpus!$I$2:$I$1045,"National") -> 355 | S14: 13 | T14: 2
A15: 11 | B15: Togo | C15: Afrique de l'Ouest | D15: =COUNTIFS(Corpus!$F$2:$F$1045,B15,Corpus!$I$2:$I$1045,"National") -> 12 | E15: =COUNTIFS(Corpus!$F$2:$F$1045,B15,Corpus!$I$2:$I$1045,"National",Corpus!$J$2:$J$1045,"<>Début du texte") -> 12 | F15: =COUNTIFS(Corpus!$F$2:$F$1045,B15,Corpus!$I$2:$I$1045,"National",Corpus!$J$2:$J$1045,"Début du texte") -> 0 | G15: 13 | H15: =IFERROR(D15/SUM($D$5:$D$59),0) -> 0.021778584 | I15: =COUNTIFS(Corpus!$F$2:$F$1045,B15,Corpus!$I$2:$I$1045,"National",Corpus!$C$2:$C$1045,2026) -> 2 | J15: =COUNTIFS(Corpus!$F$2:$F$1045,B15,Corpus!$I$2:$I$1045,"National",Corpus!$B$2:$B$1045,">="&DATE(2025,8,26)) -> 3 | K15: 44577 | L15: 46207 | M15: 52 | N15: Moyenne | O15: P3 - consolider | P15: Actualités et analyses transversales | Q15: 4 | R15: =SUMIFS(Corpus!$O$2:$O$1045,Corpus!$F$2:$F$1045,B15,Corpus!$I$2:$I$1045,"National") -> 223 | S15: 12 | T15: 0
A16: 12 | B16: Tanzanie | C16: Afrique de l'Est | D16: =COUNTIFS(Corpus!$F$2:$F$1045,B16,Corpus!$I$2:$I$1045,"National") -> 11 | E16: =COUNTIFS(Corpus!$F$2:$F$1045,B16,Corpus!$I$2:$I$1045,"National",Corpus!$J$2:$J$1045,"<>Début du texte") -> 11 | F16: =COUNTIFS(Corpus!$F$2:$F$1045,B16,Corpus!$I$2:$I$1045,"National",Corpus!$J$2:$J$1045,"Début du texte") -> 0 | G16: 19 | H16: =IFERROR(D16/SUM($D$5:$D$59),0) -> 0.019963702 | I16: =COUNTIFS(Corpus!$F$2:$F$1045,B16,Corpus!$I$2:$I$1045,"National",Corpus!$C$2:$C$1045,2026) -> 2 | J16: =COUNTIFS(Corpus!$F$2:$F$1045,B16,Corpus!$I$2:$I$1045,"National",Corpus!$B$2:$B$1045,">="&DATE(2025,8,26)) -> 3 | K16: 45089 | L16: 46216 | M16: 43 | N16: Moyenne | O16: P3 - consolider | P16: One Health, zoonoses et santé publique | Q16: 5 | R16: =SUMIFS(Corpus!$O$2:$O$1045,Corpus!$F$2:$F$1045,B16,Corpus!$I$2:$I$1045,"National") -> 188 | S16: 11 | T16: 0
... A55: 51 | B55: Sierra Leone | C55: Afrique de l'Ouest | D55: =COUNTIFS(Corpus!$F$2:$F$1045,B55,Corpus!$I$2:$I$1045,"National") -> 1 | E55: =COUNTIFS(Corpus!$F$2:$F$1045,B55,Corpus!$I$2:$I$1045,"National",Corpus!$J$2:$J$1045,"<>Début du texte") -> 1 | F55: =COUNTIFS(Corpus!$F$2:$F$1045,B55,Corpus!$I$2:$I$1045,"National",Corpus!$J$2:$J$1045,"Début du texte") -> 0 | G55: 2 | H55: =IFERROR(D55/SUM($D$5:$D$59),0) -> 0.001814882 | I55: =COUNTIFS(Corpus!$F$2:$F$1045,B55,Corpus!$I$2:$I$1045,"National",Corpus!$C$2:$C$1045,2026) -> 0 | J55: =COUNTIFS(Corpus!$F$2:$F$1045,B55,Corpus!$I$2:$I$1045,"National",Corpus!$B$2:$B$1045,">="&DATE(2025,8,26)) -> 0 | K55: 45822 | L55: 45822 | M55: 437 | N55: Très faible | O55: P1 - relancer rapidement | P55: One Health, zoonoses et santé publique | Q55: 1 | R55: =SUMIFS(Corpus!$O$2:$O$1045,Corpus!$F$2:$F$1045,B55,Corpus!$I$2:$I$1045,"National") -> 36 | S55: 1 | T55: 0
A56: 52 | B56: Libye | C56: Afrique du Nord | D56: =COUNTIFS(Corpus!$F$2:$F$1045,B56,Corpus!$I$2:$I$1045,"National") -> 0 | E56: =COUNTIFS(Corpus!$F$2:$F$1045,B56,Corpus!$I$2:$I$1045,"National",Corpus!$J$2:$J$1045,"<>Début du texte") -> 0 | F56: =COUNTIFS(Corpus!$F$2:$F$1045,B56,Corpus!$I$2:$I$1045,"National",Corpus!$J$2:$J$1045,"Début du texte") -> 0 | G56: 1 | H56: =IFERROR(D56/SUM($D$5:$D$59),0) -> 0 | I56: =COUNTIFS(Corpus!$F$2:$F$1045,B56,Corpus!$I$2:$I$1045,"National",Corpus!$C$2:$C$1045,2026) -> 0 | J56: =COUNTIFS(Corpus!$F$2:$F$1045,B56,Corpus!$I$2:$I$1045,"National",Corpus!$B$2:$B$1045,">="&DATE(2025,8,26)) -> 0 | N56: Nulle | O56: P1 - lancer la couverture | Q56: 0 | R56: =SUMIFS(Corpus!$O$2:$O$1045,Corpus!$F$2:$F$1045,B56,Corpus!$I$2:$I$1045,"National") -> 0 | S56: 0 | T56: 0
A57: 53 | B57: RASD / Sahara occidental | C57: Afrique du Nord | D57: =COUNTIFS(Corpus!$F$2:$F$1045,B57,Corpus!$I$2:$I$1045,"National") -> 0 | E57: =COUNTIFS(Corpus!$F$2:$F$1045,B57,Corpus!$I$2:$I$1045,"National",Corpus!$J$2:$J$1045,"<>Début du texte") -> 0 | F57: =COUNTIFS(Corpus!$F$2:$F$1045,B57,Corpus!$I$2:$I$1045,"National",Corpus!$J$2:$J$1045,"Début du texte") -> 0 | G57: 0 | H57: =IFERROR(D57/SUM($D$5:$D$59),0) -> 0 | I57: =COUNTIFS(Corpus!$F$2:$F$1045,B57,Corpus!$I$2:$I$1045,"National",Corpus!$C$2:$C$1045,2026) -> 0 | J57: =COUNTIFS(Corpus!$F$2:$F$1045,B57,Corpus!$I$2:$I$1045,"National",Corpus!$B$2:$B$1045,">="&DATE(2025,8,26)) -> 0 | N57: Nulle | O57: P1 - lancer la couverture | Q57: 0 | R57: =SUMIFS(Corpus!$O$2:$O$1045,Corpus!$F$2:$F$1045,B57,Corpus!$I$2:$I$1045,"National") -> 0 | S57: 0 | T57: 0
A58: 54 | B58: Sao Tomé-et-Principe | C58: Afrique centrale | D58: =COUNTIFS(Corpus!$F$2:$F$1045,B58,Corpus!$I$2:$I$1045,"National") -> 0 | E58: =COUNTIFS(Corpus!$F$2:$F$1045,B58,Corpus!$I$2:$I$1045,"National",Corpus!$J$2:$J$1045,"<>Début du texte") -> 0 | F58: =COUNTIFS(Corpus!$F$2:$F$1045,B58,Corpus!$I$2:$I$1045,"National",Corpus!$J$2:$J$1045,"Début du texte") -> 0 | G58: 0 | H58: =IFERROR(D58/SUM($D$5:$D$59),0) -> 0 | I58: =COUNTIFS(Corpus!$F$2:$F$1045,B58,Corpus!$I$2:$I$1045,"National",Corpus!$C$2:$C$1045,2026) -> 0 | J58: =COUNTIFS(Corpus!$F$2:$F$1045,B58,Corpus!$I$2:$I$1045,"National",Corpus!$B$2:$B$1045,">="&DATE(2025,8,26)) -> 0 | N58: Nulle | O58: P1 - lancer la couverture | Q58: 0 | R58: =SUMIFS(Corpus!$O$2:$O$1045,Corpus!$F$2:$F$1045,B58,Corpus!$I$2:$I$1045,"National") -> 0 | S58: 0 | T58: 0
A59: 55 | B59: Érythrée | C59: Afrique de l'Est | D59: =COUNTIFS(Corpus!$F$2:$F$1045,B59,Corpus!$I$2:$I$1045,"National") -> 0 | E59: =COUNTIFS(Corpus!$F$2:$F$1045,B59,Corpus!$I$2:$I$1045,"National",Corpus!$J$2:$J$1045,"<>Début du texte") -> 0 | F59: =COUNTIFS(Corpus!$F$2:$F$1045,B59,Corpus!$I$2:$I$1045,"National",Corpus!$J$2:$J$1045,"Début du texte") -> 0 | G59: 0 | H59: =IFERROR(D59/SUM($D$5:$D$59),0) -> 0 | I59: =COUNTIFS(Corpus!$F$2:$F$1045,B59,Corpus!$I$2:$I$1045,"National",Corpus!$C$2:$C$1045,2026) -> 0 | J59: =COUNTIFS(Corpus!$F$2:$F$1045,B59,Corpus!$I$2:$I$1045,"National",Corpus!$B$2:$B$1045,">="&DATE(2025,8,26)) -> 0 | N59: Nulle | O59: P1 - lancer la couverture | Q59: 0 | R59: =SUMIFS(Corpus!$O$2:$O$1045,Corpus!$F$2:$F$1045,B59,Corpus!$I$2:$I$1045,"National") -> 0 | S59: 0 | T59: 0

Sheet Corpus
A1: ID | B1: Date | C1: Année | D1: Titre | E1: URL | F1: Pays principal | G1: Autres pays UA | H1: Région UA | I1: Portée | J1: Méthode d’attribution | K1: Confiance | L1: Catégorie | M1: Macrothème | N1: Langue détectée | O1: Vues | P1: Auteur | Q1: Champ pays source | R1: Slug
A2: 1501 | B2: 46259 | C2: 2026 | D2: Eswatini Reopens Breeding-Livestock Imports Under Strict Disease Controls | E2: https://www.africavet.com/article/eswatini-reopens-breeding-livestock-imports-under-strict-disease-controls | F2: Eswatini | H2: Afrique australe | I2: National | J2: Champ pays | K2: Élevée | L2: Productions animales | M2: Actualités et analyses transversales | N2: EN | O2: 4 | P2: Malick Kane | Q2: Eswatini | R2: eswatini-reopens-breeding-livestock-imports-under-strict-disease-controls
A3: 1500 | B3: 46259 | C3: 2026 | D3: Kenya: Meat Expo 2026 Puts Veterinary Paraprofessionals in the Spotlight | E3: https://www.africavet.com/article/kenya-meat-expo-2026-puts-veterinary-paraprofessionals-in-the-spotlight | F3: Kenya | H3: Afrique de l'Est | I3: National | J3: Champ pays | K3: Élevée | L3: Breaking news | M3: Profession et services vétérinaires | N3: EN | O3: 8 | P3: Malick Kane | Q3: Kenya | R3: kenya-meat-expo-2026-puts-veterinary-paraprofessionals-in-the-spotlight
A4: 1499 | B4: 46259 | C4: 2026 | D4: Djibouti : quatre nouveaux investissements pour renforcer l’élevage et les filières alimentaires | E4: https://www.africavet.com/article/djibouti-quatre-nouveaux-investissements-pour-renforcer-lelevage-et-les-filieres-alimentaires | F4: Djibouti | H4: Afrique de l'Est | I4: National | J4: Champ pays | K4: Élevée | L4: Elévage | M4: Élevage et productions animales | N4: FR | O4: 10 | P4: Malick Kane | Q4: Djibouti | R4: djibouti-quatre-nouveaux-investissements-pour-renforcer-lelevage-et-les-filieres-alimentaires
A5: 1498 | B5: 46259 | C5: 2026 | D5: South Sudan: 8,688 Pigs Die in Yambio as African Swine Fever Is Suspected | E5: https://www.africavet.com/article/south-sudan-8688-pigs-die-in-yambio-as-african-swine-fever-is-suspected | F5: Soudan du Sud | H5: Afrique de l'Est | I5: National | J5: Champ pays | K5: Élevée | L5: Maladies porcines | M5: Santé animale et maladies | N5: EN | O5: 7 | P5: Malick Kane | Q5: South Sudan | R5: south-sudan-8688-pigs-die-in-yambio-as-african-swine-fever-is-suspected
A6: 1497 | B6: 46259 | C6: 2026 | D6: Tchad : à Abéché, un abattoir moderne annoncé face aux défis sanitaires de la filière viande | E6: https://www.africavet.com/article/tchad-a-abeche-un-abattoir-moderne-annonce-face-aux-defis-sanitaires-de-la-filiere-viande | F6: Tchad | H6: Afrique centrale | I6: National | J6: Champ pays | K6: Élevée | L6: Actualités | M6: Actualités et analyses transversales | N6: FR | O6: 3 | P6: Malick Kane | Q6: Tchad | R6: tchad-a-abeche-un-abattoir-moderne-annonce-face-aux-defis-sanitaires-de-la-filiere-viande
A7: 1496 | B7: 46259 | C7: 2026 | D7: Cameroun : le CNFZV de Foumban forme 153 nouveaux professionnels des filières animales | E7: https://www.africavet.com/article/cameroun-le-cnfzv-de-foumban-forme-153-nouveaux-professionnels-des-filieres-animales | F7: Cameroun | H7: Afrique centrale | I7: National | J7: Champ pays | K7: Élevée | L7: Services vétérinaires | M7: Actualités et analyses transversales | N7: FR | O7: 6 | P7: Malick Kane | Q7: Cameroun | R7: cameroun-le-cnfzv-de-foumban-forme-153-nouveaux-professionnels-des-filieres-animales
A8: 1495 | B8: 46259 | C8: 2026 | D8: Sénégal : à Saint-Louis, le ministre de l’Agriculture au chevet des filières de la Vallée | E8: https://www.africavet.com/article/senegal-a-saint-louis-le-ministre-de-lagriculture-au-chevet-des-filieres-de-la-vallee | F8: Sénégal | H8: Afrique de l'Ouest | I8: National | J8: Champ pays | K8: Élevée | L8: Elévage | M8: Élevage et productions animales | N8: FR | O8: 6 | P8: Malick Kane | Q8: Sénégal | R8: senegal-a-saint-louis-le-ministre-de-lagriculture-au-chevet-des-filieres-de-la-vallee
A9: 1494 | B9: 46259 | C9: 2026 | D9: Niger : malgré le retour des pluies, la soudure pastorale fragilise encore les troupeaux | E9: https://www.africavet.com/article/niger-malgre-le-retour-des-pluies-la-soudure-pastorale-fragilise-encore-les-troupeaux | F9: Niger | H9: Afrique de l'Ouest | I9: National | J9: Champ pays | K9: Élevée | L9: Pastoralisme | M9: Élevage et productions animales | N9: FR | O9: 11 | P9: Malick Kane | Q9: Niger | R9: niger-malgre-le-retour-des-pluies-la-soudure-pastorale-fragilise-encore-les-troupeaux
A10: 1493 | B10: 46259 | C10: 2026 | D10: Malawi: Farming Practices Around Fishponds Raise Quiet Concerns for Fish and Human Health | E10: https://www.africavet.com/article/malawi-farming-practices-around-fishponds-raise-quiet-concerns-for-fish-and-human-health | F10: Malawi | H10: Afrique australe | I10: National | J10: Champ pays | K10: Élevée | L10: Aquaculture | M10: Pêches et aquaculture | N10: EN | O10: 8 | P10: Malick Kane | Q10: Malawi | R10: malawi-farming-practices-around-fishponds-raise-quiet-concerns-for-fish-and-human-health
A11: 1492 | B11: 46259 | C11: 2026 | D11: Aquatic Animal Health: WOAH Sets Global Priorities for Better Disease Prevention | E11: https://www.africavet.com/article/aquatic-animal-health-woah-sets-global-priorities-for-better-disease-prevention | I11: Continental africain | J11: Aucun pays AU détecté | K11: À vérifier | L11: Pêches | M11: Pêches et aquaculture | N11: EN | O11: 5 | P11: Malick Kane | R11: aquatic-animal-health-woah-sets-global-priorities-for-better-disease-prevention
A12: 1491 | B12: 46258 | C12: 2026 | D12: Nigeria : à Maiduguri, un nouvel hôpital vétérinaire face au défi de l’accès aux soins | E12: https://www.africavet.com/article/nigeria-a-maiduguri-un-nouvel-hopital-veterinaire-face-au-defi-de-lacces-aux-soins | F12: Nigeria | H12: Afrique de l'Ouest | I12: National | J12: Champ pays | K12: Élevée | L12: Services vétérinaires | M12: Profession et services vétérinaires | N12: FR | O12: 10 | P12: Malick Kane | Q12: Nigeria | R12: nigeria-a-maiduguri-un-nouvel-hopital-veterinaire-face-au-defi-de-lacces-aux-soins
A13: 1490 | B13: 46258 | C13: 2026 | D13: Maroc : 1,02 million d’éleveurs soutenus pour préserver les femelles et reconstruire le cheptel | E13: https://www.africavet.com/article/maroc-102-million-deleveurs-soutenus-pour-preserver-les-femelles-et-reconstruire-le-cheptel | F13: Maroc | H13: Afrique du Nord | I13: National | J13: Champ pays | K13: Élevée | L13: Elévage | M13: Élevage et productions animales | N13: FR | O13: 46 | P13: Malick Kane | Q13: Maroc | R13: maroc-102-million-deleveurs-soutenus-pour-preserver-les-femelles-et-reconstruire-le-cheptel
A14: 1489 | B14: 46258 | C14: 2026 | D14: Maroc : avec la loi 19.25, la gestion des animaux errants change de cap | E14: https://www.africavet.com/article/maroc-avec-la-loi-1925-la-gestion-des-animaux-errants-change-de-cap | F14: Maroc | H14: Afrique du Nord | I14: National | J14: Champ pays | K14: Élevée | L14: Services vétérinaires | M14: Actualités et analyses transversales | N14: FR | O14: 13 | P14: Malick Kane | Q14: Maroc | R14: maroc-avec-la-loi-1925-la-gestion-des-animaux-errants-change-de-cap
A15: 1488 | B15: 46257 | C15: 2026 | D15: Africa is Ready to Lead: CPHIA 2026 Opens the Next Chapter of African Public Health | E15: https://www.africavet.com/article/africa-is-ready-to-lead-cphia-2026-opens-the-next-chapter-of-african-public-health | I15: Continental africain | J15: Portée continentale dans le titre | K15: Élevée | L15: Call/Grants | M15: Ressources, recherche et opportunités | N15: EN | O15: 23 | P15: Malick Kane | R15: africa-is-ready-to-lead-cphia-2026-opens-the-next-chapter-of-african-public-health
A16: 1487 | B16: 46257 | C16: 2026 | D16: Burkina Faso : les éleveurs peuvent demander et suivre en ligne une insémination artificielle | E16: https://www.africavet.com/article/burkina-faso-les-eleveurs-peuvent-demander-et-suivre-en-ligne-une-insemination-artificielle | F16: Burkina Faso | H16: Afrique de l'Ouest | I16: National | J16: Champ pays | K16: Élevée | L16: Bovins et petits ruminants | M16: Élevage et productions animales | N16: FR | O16: 15 | P16: Malick Kane | Q16: Burkina Faso | R16: burkina-faso-les-eleveurs-peuvent-demander-et-suivre-en-ligne-une-insemination-artificielle
A17: 1486 | B17: 46257 | C17: 2026 | D17: Burkina Faso : les régions mobilisées pour la campagne de vaccination animale 2026-2027 | E17: https://www.africavet.com/article/burkina-faso-les-regions-mobilisees-pour-la-campagne-de-vaccination-animale-2026-2027 | F17: Burkina Faso | H17: Afrique de l'Ouest | I17: National | J17: Champ pays | K17: Élevée | L17: Maladies des ruminants | M17: Santé animale et maladies | N17: FR | O17: 34 | P17: Malick Kane | Q17: Burkina Faso | R17: burkina-faso-les-regions-mobilisees-pour-la-campagne-de-vaccination-animale-2026-2027
A18: 1485 | B18: 46257 | C18: 2026 | D18: Madagascar : vétérinaires et forces de l’ordre testent leur riposte face à l’agrocriminalité | E18: https://www.africavet.com/article/madagascar-veterinaires-et-forces-de-lordre-testent-leur-riposte-face-a-lagrocriminalite | F18: Madagascar | H18: Afrique de l'Est | I18: National | J18: Champ pays | K18: Élevée | L18: One Health | M18: One Health, zoonoses et santé publique | N18: FR | O18: 26 | P18: Malick Kane | Q18: Madagascar | R18: madagascar-veterinaires-et-forces-de-lordre-testent-leur-riposte-face-a-lagrocriminalite
A19: 1484 | B19: 46256 | C19: 2026 | D19: CALL FOR ABSTRACTS : Conference on Human-Wildlife Coexistence | E19: https://www.africavet.com/article/call-for-abstracts-conference-on-human-wildlife-coexistence | I19: Non attribué | J19: Aucun pays AU détecté | K19: À vérifier | L19: Call/Grants | M19: Ressources, recherche et opportunités | N19: EN | O19: 16 | P19: Malick Kane | R19: call-for-abstracts-conference-on-human-wildlife-coexistence
A20: 1483 | B20: 46256 | C20: 2026 | D20: Nigeria: UK-funded programme targets safer meat, eggs, fish and honey for export markets | E20: https://www.africavet.com/article/nigeria-uk-funded-programme-targets-safer-meat-eggs-fish-and-honey-for-export-markets | F20: Nigeria | H20: Afrique de l'Ouest | I20: National | J20: Champ pays | K20: Élevée | L20: Elévage | M20: Élevage et productions animales | N20: EN | O20: 22 | P20: Malick Kane | Q20: Nigeria | R20: nigeria-uk-funded-programme-targets-safer-meat-eggs-fish-and-honey-for-export-markets
A21: 1482 | B21: 46256 | C21: 2026 | D21: Afrique : jusqu’à 65 000 dollars pour financer la recherche sur les maladies tropicales négligées | E21: https://www.africavet.com/article/afrique-jusqua-65-000-dollars-pour-financer-la-recherche-sur-les-maladies-tropicales-negligees | I21: Continental africain | J21: Portée continentale dans le titre | K21: Élevée | L21: Call/Grants | M21: Ressources, recherche et opportunités | N21: FR | O21: 23 | P21: Malick Kane | R21: afrique-jusqua-65-000-dollars-pour-financer-la-recherche-sur-les-maladies-tropicales-negligees
A22: 1481 | B22: 46256 | C22: 2026 | D22: Cameroun : 6,5 milliards FCFA supplémentaires pour financer l’élevage bovin, le lait et le poisson | E22: https://www.africavet.com/article/cameroun-65-milliards-fcfa-supplementaires-pour-financer-lelevage-bovin-le-lait-et-le-poisson | F22: Cameroun | H22: Afrique centrale | I22: National | J22: Champ pays | K22: Élevée | L22: Elévage | M22: Élevage et productions animales | N22: FR | O22: 61 | P22: Malick Kane | Q22: Cameroun | R22: cameroun-65-milliards-fcfa-supplementaires-pour-financer-lelevage-bovin-le-lait-et-le-poisson
A23: 1480 | B23: 46256 | C23: 2026 | D23: Antibiotiques chez les poulets : pourquoi traiter sans diagnostic peut être une erreur | E23: https://www.africavet.com/article/antibiotiques-chez-les-poulets-pourquoi-traiter-sans-diagnostic-peut-etre-une-erreur | I23: Non attribué | J23: Aucun pays AU détecté | K23: À vérifier | L23: Guides | M23: Ressources, recherche et opportunités | N23: FR | O23: 18 | P23: Malick Kane | R23: antibiotiques-chez-les-poulets-pourquoi-traiter-sans-diagnostic-peut-etre-une-erreur
A24: 1479 | B24: 46255 | C24: 2026 | D24: Sénégal : 969 millions FCFA pour produire localement des œufs à couver et réduire la dépendance avicole | E24: https://www.africavet.com/article/senegal-969-millions-fcfa-pour-produire-localement-des-oeufs-a-couver-et-reduire-la-dependance-avicole | F24: Sénégal | H24: Afrique de l'Ouest | I24: National | J24: Champ pays | K24: Élevée | L24: Aviculture | M24: Élevage et productions animales | N24: FR | O24: 16 | P24: Malick Kane | Q24: Sénégal | R24: senegal-969-millions-fcfa-pour-produire-localement-des-oeufs-a-couver-et-reduire-la-dependance-avicole
A25: 1478 | B25: 46255 | C25: 2026 | D25: WHO/TDR Call for Proposals: Up to US$15,000 for Health and One Health Research in Africa | E25: https://www.africavet.com/article/whotdr-call-for-proposals-up-to-usdollar15000-for-health-and-one-health-research-in-africa | I25: Continental africain | J25: Portée continentale dans le titre | K25: Élevée | L25: Call/Grants | M25: Ressources, recherche et opportunités | N25: EN | O25: 36 | P25: Malick Kane | R25: whotdr-call-for-proposals-up-to-usdollar15000-for-health-and-one-health-research-in-africa
A26: 1477 | B26: 46255 | C26: 2026 | D26: Intelligence artificielle et agriculture : la FAO et Smart Africa mobilisent 50 000 USD pour déployer une solution en Afrique | E26: https://www.africavet.com/article/intelligence-artificielle-et-agriculture-la-fao-et-smart-africa-mobilisent-50-000-usd-pour-deployer-une-solution-en-afrique | I26: Continental africain | J26: Portée continentale dans le titre | K26: Élevée | L26: Bourses | M26: Ressources, recherche et opportunités | N26: FR | O26: 18 | P26: Malick Kane | R26: intelligence-artificielle-et-agriculture-la-fao-et-smart-africa-mobilisent-50-000-usd-pour-deployer-une-solution-en-afrique
A27: 1476 | B27: 46255 | C27: 2026 | D27: South Africa: Herpesvirus Detected in Sardines Following Mass Die-Off | E27: https://www.africavet.com/article/south-africa-herpesvirus-detected-in-sardines-following-mass-die-off | F27: Afrique du Sud | H27: Afrique australe | I27: National | J27: Champ pays | K27: Élevée | L27: Pêches | M27: Pêches et aquaculture | N27: EN | O27: 43 | P27: Malick Kane | Q27: South Africa | R27: south-africa-herpesvirus-detected-in-sardines-following-mass-die-off
A28: 1475 | B28: 46255 | C28: 2026 | D28: Kenya : Mystère et tensions autour de la mort d’une vingtaine d’éléphants empoisonnés | E28: https://www.africavet.com/article/kenya-mystere-et-tensions-autour-de-la-mort-dune-vingtaine-delephants-empoisonnes | F28: Kenya | H28: Afrique de l'Est | I28: National | J28: Champ pays | K28: Élevée | L28: Faune | M28: Faune et conservation | N28: FR | O28: 22 | P28: Mac Juliette Johngwe | Q28: Kenya | R28: kenya-mystere-et-tensions-autour-de-la-mort-dune-vingtaine-delephants-empoisonnes
A29: 1474 | B29: 46255 | C29: 2026 | D29: Burkina Faso : l’opération « Zéro poulailler vide » veut remettre 500 élevages avicoles en production | E29: https://www.africavet.com/article/burkina-faso-loperation-zero-poulailler-vide-veut-remettre-500-elevages-avicoles-en-production | F29: Burkina Faso | H29: Afrique de l'Ouest | I29: National | J29: Champ pays | K29: Élevée | L29: Breaking news | M29: Actualités et analyses transversales | N29: FR | O29: 121 | P29: Malick Kane | Q29: Burkina Faso | R29: burkina-faso-loperation-zero-poulailler-vide-veut-remettre-500-elevages-avicoles-en-production
A30: 1473 | B30: 46255 | C30: 2026 | D30: Cameroun : 93 stages ouverts dans des projets financés par la BAD, dont huit au PDCVEP | E30: https://www.africavet.com/article/cameroun-93-stages-ouverts-dans-des-projets-finances-par-la-bad-dont-huit-au-pdcvep | F30: Cameroun | H30: Afrique centrale | I30: National | J30: Champ pays | K30: Élevée | L30: Call/Grants | M30: Ressources, recherche et opportunités | N30: FR | O30: 75 | P30: Malick Kane | Q30: Cameroun | R30: cameroun-93-stages-ouverts-dans-des-projets-finances-par-la-bad-dont-huit-au-pdcvep
A31: 1472 | B31: 46254 | C31: 2026 | D31: Virus Shamonda : l’alerte bovine s’étend en Europe et interpelle l’Afrique | E31: https://www.africavet.com/article/virus-shamonda-lalerte-bovine-setend-en-europe-et-interpelle-lafrique | I31: Continental africain | J31: Portée continentale dans le titre | K31: Élevée | L31: Actualités | M31: Actualités et analyses transversales | N31: FR | O31: 52 | P31: Malick Kane | R31: virus-shamonda-lalerte-bovine-setend-en-europe-et-interpelle-lafrique
A32: 1471 | B32: 46254 | C32: 2026 | D32: Coccidiose chez les poulets : ces signes discrets qui peuvent coûter cher à l’éleveur | E32: https://www.africavet.com/article/coccidiose-chez-les-poulets-ces-signes-discrets-qui-peuvent-couter-cher-a-leleveur | I32: Non attribué | J32: Aucun pays AU détecté | K32: À vérifier | L32: Guides | M32: Ressources, recherche et opportunités | N32: FR | O32: 181 | P32: Malick Kane | R32: coccidiose-chez-les-poulets-ces-signes-discrets-qui-peuvent-couter-cher-a-leleveur
A33: 1470 | B33: 46254 | C33: 2026 | D33: PPR : les « épisystèmes », un levier stratégique pour le PAPS et l’éradication en Afrique | E33: https://www.africavet.com/article/ppr-les-episystemes-un-levier-strategique-pour-le-paps-et-leradication-en-afrique | I33: Continental africain | J33: Portée continentale dans le titre | K33: Élevée | L33: News | M33: Actualités et analyses transversales | N33: FR | O33: 91 | P33: Malick Kane | R33: ppr-les-episystemes-un-levier-strategique-pour-le-paps-et-leradication-en-afrique
A34: 1469 | B34: 46253 | C34: 2026 | D34: Tunisie : jusqu’à 150 moutons et chèvres morts à Métlaoui, les analyses doivent trancher | E34: https://www.africavet.com/article/tunisie-jusqua-150-moutons-et-chevres-morts-a-metlaoui-les-analyses-doivent-trancher | F34: Tunisie | H34: Afrique du Nord | I34: National | J34: Champ pays | K34: Élevée | L34: Maladies des ruminants | M34: Santé animale et maladies | N34: FR | O34: 18 | P34: Malick Kane | Q34: Tunisie | R34: tunisie-jusqua-150-moutons-et-chevres-morts-a-metlaoui-les-analyses-doivent-trancher
A35: 1468 | B35: 46253 | C35: 2026 | D35: South Sudan Faces Growing Cross-Border Ebola Risk as Outbreak in DRC Moves Closer | E35: https://www.africavet.com/article/south-sudan-faces-growing-cross-border-ebola-risk-as-outbreak-in-drc-moves-closer | F35: Soudan du Sud | H35: Afrique de l'Est | I35: National | J35: Champ pays | K35: Élevée | L35: Non renseignée | M35: Actualités et analyses transversales | N35: EN | O35: 12 | P35: Mac Juliette Johngwe | Q35: South Sudan | R35: south-sudan-faces-growing-cross-border-ebola-risk-as-outbreak-in-drc-moves-closer
A36: 1467 | B36: 46252 | C36: 2026 | D36: Deux lions, trois pays : un voyage exceptionnel à travers l’Afrique | E36: https://www.africavet.com/article/deux-lions-trois-pays-un-voyage-exceptionnel-a-travers-lafrique | I36: Continental africain | J36: Portée continentale dans le titre | K36: Élevée | L36: Conservation | M36: Faune et conservation | N36: FR | O36: 12 | P36: Mac Juliette Johngwe | R36: deux-lions-trois-pays-un-voyage-exceptionnel-a-travers-lafrique
A37: 1466 | B37: 46252 | C37: 2026 | D37: Cap-Vert : 18 épidémiologistes de terrain pour transformer les alertes sanitaires en actions | E37: https://www.africavet.com/article/cap-vert-18-epidemiologistes-de-terrain-pour-transformer-les-alertes-sanitaires-en-actions | F37: Cabo Verde | H37: Afrique de l'Ouest | I37: National | J37: Champ pays | K37: Élevée | L37: Vets | M37: Profession et services vétérinaires | N37: FR | O37: 20 | P37: Malick Kane | Q37: Cap-Vert | R37: cap-vert-18-epidemiologistes-de-terrain-pour-transformer-les-alertes-sanitaires-en-actions
A38: 1465 | B38: 46252 | C38: 2026 | D38: Madagascar : un poulet sur cinq meurt avant le marché, la santé animale peut inverser la tendance | E38: https://www.africavet.com/article/madagascar-un-poulet-sur-cinq-meurt-avant-le-marche-la-sante-animale-peut-inverser-la-tendance | F38: Madagascar | H38: Afrique de l'Est | I38: National | J38: Champ pays | K38: Élevée | L38: Maladies aviaires | M38: Santé animale et maladies | N38: FR | O38: 19 | P38: Malick Kane | Q38: Madagascar | R38: madagascar-un-poulet-sur-cinq-meurt-avant-le-marche-la-sante-animale-peut-inverser-la-tendance
A39: 1464 | B39: 46252 | C39: 2026 | D39: À Maurice, les démarches vétérinaires passent au numérique pour sécuriser le commerce animal | E39: https://www.africavet.com/article/a-maurice-les-demarches-veterinaires-passent-au-numerique-pour-securiser-le-commerce-animal | F39: Maurice | H39: Afrique de l'Est | I39: National | J39: Titre/slug | K39: Élevée | L39: Innovation | M39: Actualités et analyses transversales | N39: FR | O39: 16 | P39: Malick Kane | Q39: Maurice | R39: a-maurice-les-demarches-veterinaires-passent-au-numerique-pour-securiser-le-commerce-animal
A40: 1463 | B40: 46251 | C40: 2026 | D40: Comores : le nouveau Code de l’élevage ouvre une nouvelle ère pour la santé animale | E40: https://www.africavet.com/article/comores-le-nouveau-code-de-lelevage-ouvre-une-nouvelle-ere-pour-la-sante-animale | F40: Comores | H40: Afrique de l'Est | I40: National | J40: Champ pays | K40: Élevée | L40: Santé publique vétérinaire | M40: Actualités et analyses transversales | N40: FR | O40: 58 | P40: Malick Kane | Q40: Comores | R40: comores-le-nouveau-code-de-lelevage-ouvre-une-nouvelle-ere-pour-la-sante-animale
A41: 1462 | B41: 46251 | C41: 2026 | D41: Over 1,000 Pigs Dead as African Swine Fever Strikes Kiambu | E41: https://www.africavet.com/article/over-1000-pigs-dead-as-african-swine-fever-strikes-kiambu | F41: Kenya | H41: Afrique de l'Est | I41: National | J41: Champ pays | K41: Élevée | L41: Diseases | M41: Santé animale et maladies | N41: EN | O41: 33 | P41: Mac Juliette Johngwe | Q41: Kenya | R41: over-1000-pigs-dead-as-african-swine-fever-strikes-kiambu
A42: 1461 | B42: 46250 | C42: 2026 | D42: Chenille légionnaire africaine : pourquoi une invasion des pâturages peut aussi menacer les bovins | E42: https://www.africavet.com/article/chenille-legionnaire-africaine-pourquoi-une-invasion-des-paturages-peut-aussi-menacer-les-bovins | F42: Afrique du Sud | H42: Afrique australe | I42: National | J42: Chapeau | K42: Moyenne | L42: Guides | M42: Ressources, recherche et opportunités | N42: FR | O42: 20 | P42: Malick Kane | R42: chenille-legionnaire-africaine-pourquoi-une-invasion-des-paturages-peut-aussi-menacer-les-bovins
A43: 1460 | B43: 46250 | C43: 2026 | D43: Sénégal : à Kaffrine, l’usage des antibiotiques dans les troupeaux révèle un défi One Health | E43: https://www.africavet.com/article/senegal-a-kaffrine-lusage-des-antibiotiques-dans-les-troupeaux-revele-un-defi-one-health | F43: Sénégal | H43: Afrique de l'Ouest | I43: National | J43: Champ pays | K43: Élevée | L43: Antibiorésistance | M43: One Health, zoonoses et santé publique | N43: FR | O43: 29 | P43: Malick Kane | Q43: Sénégal | R43: senegal-a-kaffrine-lusage-des-antibiotiques-dans-les-troupeaux-revele-un-defi-one-health
A44: 1459 | B44: 46249 | C44: 2026 | D44: 2026 Call for Nominations for AAS Fellowship | E44: https://www.africavet.com/article/2026-call-for-nominations-for-aas-fellowship | I44: Non attribué | J44: Aucun pays AU détecté | K44: À vérifier | L44: Call/Grants | M44: Ressources, recherche et opportunités | N44: EN | O44: 38 | P44: Malick Kane | R44: 2026-call-for-nominations-for-aas-fellowship
A45: 1458 | B45: 46249 | C45: 2026 | D45: Bovins en Afrique de l’Ouest : mieux nourrir avec les ressources locales plutôt que nourrir davantage | E45: https://www.africavet.com/article/bovins-en-afrique-de-louest-mieux-nourrir-avec-les-ressources-locales-plutot-que-nourrir-davantage | H45: Afrique de l'Ouest | I45: Régional africain | J45: Portée régionale dans le titre | K45: Élevée | L45: Breaking news | M45: Actualités et analyses transversales | N45: FR | O45: 31 | P45: Malick Kane | R45: bovins-en-afrique-de-louest-mieux-nourrir-avec-les-ressources-locales-plutot-que-nourrir-davantage
A46: 1457 | B46: 46249 | C46: 2026 | D46: La biosécurité commence avant l’épidémie : le SAVC rappelle que les personnes sont la première ligne de défense | E46: https://www.africavet.com/article/la-biosecurite-commence-avant-lepidemie-le-savc-rappelle-que-les-personnes-sont-la-premiere-ligne-de-defense | F46: Afrique du Sud | H46: Afrique australe | I46: National | J46: Champ pays | K46: Élevée | L46: Santé animale | M46: Santé animale et maladies | N46: FR | O46: 18 | P46: Mac Juliette Johngwe | Q46: South Africa | R46: la-biosecurite-commence-avant-lepidemie-le-savc-rappelle-que-les-personnes-sont-la-premiere-ligne-de-defense
A47: 1456 | B47: 46248 | C47: 2026 | D47: Abnormal chicken droppings: What their colour can reveal — and what it cannot diagnose | E47: https://www.africavet.com/article/abnormal-chicken-droppings-what-their-colour-can-reveal-and-what-it-cannot-diagnose | I47: Non attribué | J47: Aucun pays AU détecté | K47: À vérifier | L47: Fiches techniques | M47: Ressources, recherche et opportunités | N47: EN | O47: 22 | P47: Malick Kane | R47: abnormal-chicken-droppings-what-their-colour-can-reveal-and-what-it-cannot-diagnose
A48: 1455 | B48: 46248 | C48: 2026 | D48: Fientes anormales chez les poulets : ce que leur couleur peut révéler — et ce qu’elle ne permet pas de diagnostiquer | E48: https://www.africavet.com/article/fientes-anormales-chez-les-poulets-ce-que-leur-couleur-peut-reveler-et-ce-quelle-ne-permet-pas-de-diagnostiquer | I48: Non attribué | J48: Aucun pays AU détecté | K48: À vérifier | L48: Fiches techniques | M48: Ressources, recherche et opportunités | N48: FR | O48: 66 | P48: Malick Kane | R48: fientes-anormales-chez-les-poulets-ce-que-leur-couleur-peut-reveler-et-ce-quelle-ne-permet-pas-de-diagnostiquer
A49: 1454 | B49: 46248 | C49: 2026 | D49: Namibia Responds to Confirmed Rabies Case in Ondangwa with Emergency Vaccination Campaign | E49: https://www.africavet.com/article/namibia-responds-to-confirmed-rabies-case-in-ondangwa-with-emergency-vaccination-campaign | F49: Namibie | H49: Afrique australe | I49: National | J49: Champ pays | K49: Élevée | L49: Rage | M49: One Health, zoonoses et santé publique | N49: EN | O49: 47 | P49: Mac Juliette Johngwe | Q49: Namibia | R49: namibia-responds-to-confirmed-rabies-case-in-ondangwa-with-emergency-vaccination-campaign
A50: 1453 | B50: 46246 | C50: 2026 | D50: Poulets qui meurent subitement : les 7 vérifications à faire avant de traiter | E50: https://www.africavet.com/article/poulets-qui-meurent-subitement-les-7-verifications-a-faire-avant-de-traiter | I50: Non attribué | J50: Aucun pays AU détecté | K50: À vérifier | L50: Vets | M50: Profession et services vétérinaires | N50: FR | O50: 63 | P50: Malick Kane | R50: poulets-qui-meurent-subitement-les-7-verifications-a-faire-avant-de-traiter
A51: 1452 | B51: 46246 | C51: 2026 | D51: Fièvre aphteuse en Afrique du Sud : RMIS lance une plateforme de commande et sécurise 4,5 millions de doses | E51: https://www.africavet.com/article/fievre-aphteuse-en-afrique-du-sud-rmis-lance-une-plateforme-de-commande-et-securise-45-millions-de-doses | F51: Afrique du Sud | H51: Afrique australe | I51: National | J51: Titre/slug | K51: Élevée | L51: Sécurité Sanitaire | M51: One Health, zoonoses et santé publique | N51: FR | O51: 28 | P51: Mac Juliette Johngwe | R51: fievre-aphteuse-en-afrique-du-sud-rmis-lance-une-plateforme-de-commande-et-securise-45-millions-de-doses
A52: 1451 | B52: 46246 | C52: 2026 | D52: Lake Victoria: Cage aquaculture is expanding, but biosecurity must keep pace | E52: https://www.africavet.com/article/lake-victoria-cage-aquaculture-is-expanding-but-biosecurity-must-keep-pace | F52: Kenya | H52: Afrique de l'Est | I52: National | J52: Champ pays | K52: Élevée | L52: Diseases | M52: Santé animale et maladies | N52: EN | O52: 43 | P52: Malick Kane | Q52: Kenya | R52: lake-victoria-cage-aquaculture-is-expanding-but-biosecurity-must-keep-pace
A53: 1450 | B53: 46245 | C53: 2026 | D53: West Africa trains One Health experts to turn regional plans into measurable results | E53: https://www.africavet.com/article/west-africa-trains-one-health-experts-to-turn-regional-plans-into-measurable-results | H53: Afrique de l'Ouest | I53: Régional africain | J53: Portée régionale dans le titre | K53: Élevée | L53: Breaking news | M53: Actualités et analyses transversales | N53: EN | O53: 46 | P53: Malick Kane | R53: west-africa-trains-one-health-experts-to-turn-regional-plans-into-measurable-results
A54: 1449 | B54: 46245 | C54: 2026 | D54: Ghana: women bushmeat traders make food safety a priority in Kumasi | E54: https://www.africavet.com/article/ghana-women-bushmeat-traders-make-food-safety-a-priority-in-kumasi | F54: Ghana | H54: Afrique de l'Ouest | I54: National | J54: Titre/slug | K54: Élevée | L54: Interface faune-bétail | M54: Faune et conservation | N54: EN | O54: 34 | P54: Malick Kane | R54: ghana-women-bushmeat-traders-make-food-safety-a-priority-in-kumasi
A55: 1448 | B55: 46245 | C55: 2026 | D55: Incendies de forêt : pour les animaux aussi, chaque minute compte | E55: https://www.africavet.com/article/incendies-de-foret-pour-les-animaux-aussi-chaque-minute-compte | I55: Non attribué | J55: Aucun pays AU détecté | K55: À vérifier | L55: Breaking news | M55: Actualités et analyses transversales | N55: FR | O55: 27 | P55: Malick Kane | R55: incendies-de-foret-pour-les-animaux-aussi-chaque-minute-compte
A56: 1447 | B56: 46245 | C56: 2026 | D56: Avian Influenza in June–July 2026: An Exceptional Wildlife Threat and a Continuing Challenge for Africa | E56: https://www.africavet.com/article/avian-influenza-in-june-july-2026-an-exceptional-wildlife-threat-and-a-continuing-challenge-for-africa | I56: Continental africain | J56: Portée continentale dans le titre | K56: Élevée | L56: Aviculture | M56: Élevage et productions animales | N56: EN | O56: 24 | P56: Mac Juliette Johngwe | R56: avian-influenza-in-june-july-2026-an-exceptional-wildlife-threat-and-a-continuing-challenge-for-africa
A57: 1446 | B57: 46245 | C57: 2026 | D57: Nigeria moves to develop its first national strategy against Newcastle disease | E57: https://www.africavet.com/article/nigeria-moves-to-develop-its-first-national-strategy-against-newcastle-disease | F57: Nigeria | H57: Afrique de l'Ouest | I57: National | J57: Champ pays | K57: Élevée | L57: Maladies aviaires | M57: Santé animale et maladies | N57: EN | O57: 28 | P57: Malick Kane | Q57: Nigeria | R57: nigeria-moves-to-develop-its-first-national-strategy-against-newcastle-disease
A58: 1445 | B58: 46245 | C58: 2026 | D58: Côte d’Ivoire : l’identification électronique des animaux passe à l’échelle nationale | E58: https://www.africavet.com/article/cote-divoire-lidentification-electronique-des-animaux-passe-a-lechelle-nationale | F58: Côte d’Ivoire | H58: Afrique de l'Ouest | I58: National | J58: Champ pays | K58: Élevée | L58: Elévage | M58: Élevage et productions animales | N58: FR | O58: 48 | P58: Malick Kane | Q58: Côte d’Ivoire | R58: cote-divoire-lidentification-electronique-des-animaux-passe-a-lechelle-nationale
A59: 1444 | B59: 46245 | C59: 2026 | D59: Ebola en RDC : la génomique révèle un nouveau passage probable de l’animal à l’homme | E59: https://www.africavet.com/article/ebola-en-rdc-la-genomique-revele-un-nouveau-passage-probable-de-lanimal-a-lhomme | F59: RDC | H59: Afrique centrale | I59: National | J59: Champ pays | K59: Élevée | L59: Diseases | M59: Santé animale et maladies | N59: FR | O59: 40 | P59: Malick Kane | Q59: RDC | R59: ebola-en-rdc-la-genomique-revele-un-nouveau-passage-probable-de-lanimal-a-lhomme
A60: 1442 | B60: 46243 | C60: 2026 | D60: Kenya: Livestock Insurance Is Booming. Can It Protect Herds Before the Next Drought? | E60: https://www.africavet.com/article/kenya-livestock-insurance-is-booming-can-it-protect-herds-before-the-next-drought | F60: Kenya | H60: Afrique de l'Est | I60: National | J60: Champ pays | K60: Élevée | L60: Elévage | M60: Élevage et productions animales | N60: EN | O60: 45 | P60: Malick Kane | Q60: Kenya | R60: kenya-livestock-insurance-is-booming-can-it-protect-herds-before-the-next-drought
A61: 1441 | B61: 46243 | C61: 2026 | D61: MERS-CoV in East Africa: Why the Dromedary Camel Is Once Again a One Health Sentinel | E61: https://www.africavet.com/article/mers-cov-in-east-africa-why-the-dromedary-camel-is-once-again-a-one-health-sentinel | H61: Afrique de l'Est | I61: Régional africain | J61: Portée régionale dans le titre | K61: Élevée | L61: News | M61: Actualités et analyses transversales | N61: EN | O61: 50 | P61: Malick Kane | R61: mers-cov-in-east-africa-why-the-dromedary-camel-is-once-again-a-one-health-sentinel
A62: 1440 | B62: 46242 | C62: 2026 | D62: Tchad : après la vaccination PPR, mesurer enfin la protection réelle des troupeaux | E62: https://www.africavet.com/article/tchad-apres-la-vaccination-ppr-mesurer-enfin-la-protection-reelle-des-troupeaux | F62: Tchad | H62: Afrique centrale | I62: National | J62: Champ pays | K62: Élevée | L62: Maladies des ruminants | M62: Santé animale et maladies | N62: FR | O62: 39 | P62: Malick Kane | Q62: Tchad | R62: tchad-apres-la-vaccination-ppr-mesurer-enfin-la-protection-reelle-des-troupeaux
A63: 1439 | B63: 46241 | C63: 2026 | D63: Somalia: In Gedo, PPR vaccination must follow the real routes of livestock | E63: https://www.africavet.com/article/somalia-in-gedo-ppr-vaccination-must-follow-the-real-routes-of-livestock | F63: Somalie | H63: Afrique de l'Est | I63: National | J63: Champ pays | K63: Élevée | L63: Diseases | M63: Santé animale et maladies | N63: EN | O63: 47 | P63: Malick Kane | Q63: Somalia | R63: somalia-in-gedo-ppr-vaccination-must-follow-the-real-routes-of-livestock
A64: 1438 | B64: 46241 | C64: 2026 | D64: Congo : l’aquaculture veut changer d’échelle, mais la santé des poissons devient un enjeu clé | E64: https://www.africavet.com/article/congo-laquaculture-veut-changer-dechelle-mais-la-sante-des-poissons-devient-un-enjeu-cle | F64: République du Congo | H64: Afrique centrale | I64: National | J64: Champ pays | K64: Élevée | L64: News | M64: Actualités et analyses transversales | N64: FR | O64: 45 | P64: Malick Kane | Q64: Congo | R64: congo-laquaculture-veut-changer-dechelle-mais-la-sante-des-poissons-devient-un-enjeu-cle
A65: 1437 | B65: 46241 | C65: 2026 | D65: Kenya: 16 elephant deaths near Amboseli raise wider environmental concerns | E65: https://www.africavet.com/article/kenya-16-elephant-deaths-near-amboseli-raise-wider-environmental-concerns | F65: Kenya | H65: Afrique de l'Est | I65: National | J65: Champ pays | K65: Élevée | L65: Conservation | M65: Faune et conservation | N65: EN | O65: 31 | P65: Malick Kane | Q65: Kenya | R65: kenya-16-elephant-deaths-near-amboseli-raise-wider-environmental-concerns
A66: 1436 | B66: 46241 | C66: 2026 | D66: Afrique : 309 millions de personnes souffrent de la faim, l’aquaculture peut-elle changer la donne ? | E66: https://www.africavet.com/article/afrique-309-millions-de-personnes-souffrent-de-la-faim-laquaculture-peut-elle-changer-la-donne | I66: Continental africain | J66: Portée continentale dans le titre | K66: Élevée | L66: News | M66: Actualités et analyses transversales | N66: FR | O66: 46 | P66: Malick Kane | R66: afrique-309-millions-de-personnes-souffrent-de-la-faim-laquaculture-peut-elle-changer-la-donne
A67: 1435 | B67: 46241 | C67: 2026 | D67: Rwanda : la fièvre de la Vallée du Rift ravive l’alerte dans les élevages | E67: https://www.africavet.com/article/rwanda-la-fievre-de-la-vallee-du-rift-ravive-lalerte-dans-les-elevages | F67: Rwanda | H67: Afrique de l'Est | I67: National | J67: Champ pays | K67: Élevée | L67: Diseases | M67: Santé animale et maladies | N67: FR | O67: 38 | P67: Malick Kane | Q67: Rwanda | R67: rwanda-la-fievre-de-la-vallee-du-rift-ravive-lalerte-dans-les-elevages
A68: 1434 | B68: 46241 | C68: 2026 | D68: Foot-and-mouth disease in Southern Africa: five gaps undermining vaccination campaigns | E68: https://www.africavet.com/article/foot-and-mouth-disease-in-southern-africa-five-gaps-undermining-vaccination-campaigns | H68: Afrique australe | I68: Régional africain | J68: Portée régionale dans le titre | K68: Élevée | L68: Maladies transfrontalières | M68: Santé animale et maladies | N68: EN | O68: 30 | P68: Malick Kane | R68: foot-and-mouth-disease-in-southern-africa-five-gaps-undermining-vaccination-campaigns
A69: 1433 | B69: 46241 | C69: 2026 | D69: Afrique : l’AU-IBAR et l’AAIN s’allient pour stimuler l’emploi des jeunes dans les filières animales | E69: https://www.africavet.com/article/afrique-lau-ibar-et-laain-sallient-pour-stimuler-lemploi-des-jeunes-dans-les-filieres-animales | I69: Continental africain | J69: Portée continentale dans le titre | K69: Élevée | L69: Vets | M69: Profession et services vétérinaires | N69: FR | O69: 41 | P69: Malick Kane | R69: afrique-lau-ibar-et-laain-sallient-pour-stimuler-lemploi-des-jeunes-dans-les-filieres-animales
A70: 1432 | B70: 46240 | C70: 2026 | D70: Ebola en RDC : Alerte sur une mutation, mortalité infantile record et course au vaccin | E70: https://www.africavet.com/article/ebola-en-rdc-alerte-sur-une-mutation-mortalite-infantile-record-et-course-au-vaccin | F70: RDC | H70: Afrique centrale | I70: National | J70: Champ pays | K70: Élevée | L70: Breaking news | M70: Actualités et analyses transversales | N70: FR | O70: 38 | P70: Mac Juliette Johngwe | Q70: RDC | R70: ebola-en-rdc-alerte-sur-une-mutation-mortalite-infantile-record-et-course-au-vaccin
A71: 1431 | B71: 46238 | C71: 2026 | D71: La FAO et l’IGAD alertent sur un risque accru de Fièvre de la Vallée du Rift en raison d’un fort épisode El Niño en Afrique de l’Est | E71: https://www.africavet.com/article/la-fao-et-ligad-alertent-sur-un-risque-accru-de-fievre-de-la-vallee-du-rift-en-raison-dun-fort-episode-el-nino-en-afrique-de-lest | H71: Afrique de l'Est | I71: Régional africain | J71: Portée régionale dans le titre | K71: Élevée | L71: Breaking news | M71: Actualités et analyses transversales | N71: FR | O71: 50 | P71: Mac Juliette Johngwe | R71: la-fao-et-ligad-alertent-sur-un-risque-accru-de-fievre-de-la-vallee-du-rift-en-raison-dun-fort-episode-el-nino-en-afrique-de-lest
A72: 1430 | B72: 46237 | C72: 2026 | D72: Malawi: Epizootic Ulcerative Syndrome Threatens Wild Fish and Aquaculture | E72: https://www.africavet.com/article/malawi-epizootic-ulcerative-syndrome-threatens-wild-fish-and-aquaculture | F72: Malawi | H72: Afrique australe | I72: National | J72: Champ pays | K72: Élevée | L72: News | M72: Actualités et analyses transversales | N72: EN | O72: 65 | P72: Malick Kane | Q72: Malawi | R72: malawi-epizootic-ulcerative-syndrome-threatens-wild-fish-and-aquaculture
A73: 1429 | B73: 46237 | C73: 2026 | D73: Mauritanie : après la fièvre de la Vallée du Rift, renforcer l’alerte Une seule Santé dans les zones pastorales | E73: https://www.africavet.com/article/mauritanie-apres-la-fievre-de-la-vallee-du-rift-renforcer-lalerte-une-seule-sante-dans-les-zones-pastorales | F73: Mauritanie | H73: Afrique du Nord | I73: National | J73: Champ pays | K73: Élevée | L73: Diseases | M73: Santé animale et maladies | N73: FR | O73: 55 | P73: Malick Kane | Q73: Mauritanie | R73: mauritanie-apres-la-fievre-de-la-vallee-du-rift-renforcer-lalerte-une-seule-sante-dans-les-zones-pastorales
A74: 1428 | B74: 46236 | C74: 2026 | D74: Cameroun : la CDPM appelée à accélérer les projets de pêche et d’aquaculture | E74: https://www.africavet.com/article/cameroun-la-cdpm-appelee-a-accelerer-les-projets-de-peche-et-daquaculture | F74: Cameroun | H74: Afrique centrale | I74: National | J74: Champ pays | K74: Élevée | L74: Pêches | M74: Pêches et aquaculture | N74: FR | O74: 64 | P74: Malick Kane | Q74: Cameroun | R74: cameroun-la-cdpm-appelee-a-accelerer-les-projets-de-peche-et-daquaculture
A75: 1427 | B75: 46236 | C75: 2026 | D75: Quels poissons pondent le plus d’œufs ? En Afrique, la perche du Nil figure parmi les championnes | E75: https://www.africavet.com/article/quels-poissons-pondent-le-plus-doeufs-en-afrique-la-perche-du-nil-figure-parmi-les-championnes | I75: Continental africain | J75: Portée continentale dans le titre | K75: Élevée | L75: News | M75: Actualités et analyses transversales | N75: FR | O75: 58 | P75: Malick Kane | R75: quels-poissons-pondent-le-plus-doeufs-en-afrique-la-perche-du-nil-figure-parmi-les-championnes
A76: 1426 | B76: 46236 | C76: 2026 | D76: Sudan: Vaccinating livestock amid conflict, a cross-border logistical challenge | E76: https://www.africavet.com/article/sudan-vaccinating-livestock-amid-conflict-a-cross-border-logistical-challenge | F76: Soudan | H76: Afrique du Nord | I76: National | J76: Titre/slug | K76: Élevée | L76: Diseases | M76: Santé animale et maladies | N76: EN | O76: 78 | P76: Malick Kane | R76: sudan-vaccinating-livestock-amid-conflict-a-cross-border-logistical-challenge
A77: 1425 | B77: 46236 | C77: 2026 | D77: Cameroon: CDEN Reports 80% Budget Execution as Livestock Support Continues in the North | E77: https://www.africavet.com/article/cameroon-cden-reports-80percent-budget-execution-as-livestock-support-continues-in-the-north | F77: Cameroun | H77: Afrique centrale | I77: National | J77: Champ pays | K77: Élevée | L77: Elévage | M77: Élevage et productions animales | N77: EN | O77: 69 | P77: Malick Kane | Q77: Cameroon | R77: cameroon-cden-reports-80percent-budget-execution-as-livestock-support-continues-in-the-north
A78: 1424 | B78: 46236 | C78: 2026 | D78: Cameroun : 28 navires sur la liste provisoire des licences de pêche industrielle pour 2026 | E78: https://www.africavet.com/article/cameroun-28-navires-sur-la-liste-provisoire-des-licences-de-peche-industrielle-pour-2026 | F78: Cameroun | H78: Afrique centrale | I78: National | J78: Champ pays | K78: Élevée | L78: Pêches | M78: Pêches et aquaculture | N78: FR | O78: 47 | P78: Malick Kane | Q78: Cameroun | R78: cameroun-28-navires-sur-la-liste-provisoire-des-licences-de-peche-industrielle-pour-2026
A79: 1423 | B79: 46236 | C79: 2026 | D79: Corne de l’Afrique : la chaleur extrême pousse les dromadaires à bout | E79: https://www.africavet.com/article/corne-de-lafrique-la-chaleur-extreme-pousse-les-dromadaires-a-bout | I79: Continental africain | J79: Portée continentale dans le titre | K79: Élevée | L79: Breaking news | M79: Actualités et analyses transversales | N79: FR | O79: 41 | P79: Malick Kane | R79: corne-de-lafrique-la-chaleur-extreme-pousse-les-dromadaires-a-bout
A80: 1422 | B80: 46235 | C80: 2026 | D80: Sénégal : à Mbao, 1 000 ruches pour donner un nouvel élan à l’apiculture | E80: https://www.africavet.com/article/senegal-a-mbao-1-000-ruches-pour-donner-un-nouvel-elan-a-lapiculture | F80: Sénégal | H80: Afrique de l'Ouest | I80: National | J80: Champ pays | K80: Élevée | L80: Sécurité sanitaire des aliments | M80: One Health, zoonoses et santé publique | N80: FR | O80: 89 | P80: Malick Kane | Q80: Sénégal | R80: senegal-a-mbao-1-000-ruches-pour-donner-un-nouvel-elan-a-lapiculture
A81: 1421 | B81: 46235 | C81: 2026 | D81: Cameroun : à Maroua, les bons gestes au cœur de la sécurité des repas collectifs | E81: https://www.africavet.com/article/cameroun-a-maroua-les-bons-gestes-au-coeur-de-la-securite-des-repas-collectifs | F81: Cameroun | H81: Afrique centrale | I81: National | J81: Champ pays | K81: Élevée | L81: Sécurité Sanitaire | M81: One Health, zoonoses et santé publique | N81: FR | O81: 47 | P81: Malick Kane | Q81: Cameroon | R81: cameroun-a-maroua-les-bons-gestes-au-coeur-de-la-securite-des-repas-collectifs
A82: 1420 | B82: 46235 | C82: 2026 | D82: first Scientific Conference on Animal Health & Welfare | E82: https://www.africavet.com/article/first-scientific-conference-on-animal-health-and-welfare | I82: Non attribué | J82: Aucun pays AU détecté | K82: À vérifier | L82: Call/Grants | M82: Ressources, recherche et opportunités | N82: EN | O82: 38 | P82: Malick Kane | R82: first-scientific-conference-on-animal-health-and-welfare
A83: 1419 | B83: 46235 | C83: 2026 | D83: De la coordination continentale à l’action de terrain : l’Afrique progresse vers l’éradication de la PPR | E83: https://www.africavet.com/article/de-la-coordination-continentale-a-laction-de-terrain-lafrique-progresse-vers-leradication-de-la-ppr | I83: Continental africain | J83: Portée continentale dans le titre | K83: Élevée | L83: Non renseignée | M83: Actualités et analyses transversales | N83: FR | O83: 13 | P83: Mac Juliette Johngwe | R83: de-la-coordination-continentale-a-laction-de-terrain-lafrique-progresse-vers-leradication-de-la-ppr
A84: 1418 | B84: 46234 | C84: 2026 | D84: La FAO présente un nouveau modèle stratégique pour lutter contre les maladies animales transfrontalières | E84: https://www.africavet.com/article/la-fao-presente-un-nouveau-modele-strategique-pour-lutter-contre-les-maladies-animales-transfrontalieres | I84: Non attribué | J84: Aucun pays AU détecté | K84: À vérifier | L84: Elévage | M84: Élevage et productions animales | N84: FR | O84: 24 | P84: Mac Juliette Johngwe | R84: la-fao-presente-un-nouveau-modele-strategique-pour-lutter-contre-les-maladies-animales-transfrontalieres
A85: 1417 | B85: 46232 | C85: 2026 | D85: Élever la sécurité des aliments aquatiques : comment l’hygiène portuaire et les innovations de la chaîne du froid renforcent les chaînes de valeur durables | E85: https://www.africavet.com/article/elever-la-securite-des-aliments-aquatiques-comment-lhygiene-portuaire-et-les-innovations-de-la-chaine-du-froid-renforcent-les-chaines-de-valeur-durables | I85: Non attribué | J85: Aucun pays AU détecté | K85: À vérifier | L85: Pêche industrielle | M85: Pêches et aquaculture | N85: FR | O85: 45 | P85: Mac Juliette Johngwe | R85: elever-la-securite-des-aliments-aquatiques-comment-lhygiene-portuaire-et-les-innovations-de-la-chaine-du-froid-renforcent-les-chaines-de-valeur-durables
A86: 1416 | B86: 46231 | C86: 2026 | D86: L’Ouganda et la Chine s’allient pour lutter contre les maladies du bétail | E86: https://www.africavet.com/article/louganda-et-la-chine-sallient-pour-lutter-contre-les-maladies-du-betail | F86: Ouganda | H86: Afrique de l'Est | I86: National | J86: Champ pays | K86: Élevée | L86: Elévage | M86: Élevage et productions animales | N86: FR | O86: 24 | P86: Mac Juliette Johngwe | Q86: Uganda | R86: louganda-et-la-chine-sallient-pour-lutter-contre-les-maladies-du-betail
A87: 1415 | B87: 46230 | C87: 2026 | D87: Maladies animales transfrontalières : la FAO propose un nouveau modèle piloté par les pays | E87: https://www.africavet.com/article/maladies-animales-transfrontalieres-la-fao-propose-un-nouveau-modele-pilote-par-les-pays | I87: Continental africain | J87: Aucun pays AU détecté | K87: À vérifier | L87: Maladies transfrontalières | M87: Santé animale et maladies | N87: FR | O87: 53 | P87: Malick Kane | R87: maladies-animales-transfrontalieres-la-fao-propose-un-nouveau-modele-pilote-par-les-pays
A88: 1414 | B88: 46230 | C88: 2026 | D88: À Djerba, des pêcheurs expérimentent une alternative solaire au carburant | E88: https://www.africavet.com/article/a-djerba-des-pecheurs-experimentent-une-alternative-solaire-au-carburant | F88: Tunisie | H88: Afrique du Nord | I88: National | J88: Champ pays | K88: Élevée | L88: Pêches | M88: Pêches et aquaculture | N88: FR | O88: 31 | P88: Malick Kane | Q88: Tunisie | R88: a-djerba-des-pecheurs-experimentent-une-alternative-solaire-au-carburant
A89: 1413 | B89: 46230 | C89: 2026 | D89: À Dakar, l’EISMV place la qualité de la formation vétérinaire au cœur de son Conseil d’établissement 2026 | E89: https://www.africavet.com/article/a-dakar-leismv-place-la-qualite-de-la-formation-veterinaire-au-coeur-de-son-conseil-detablissement-2026 | F89: Sénégal | H89: Afrique de l'Ouest | I89: National | J89: Champ pays | K89: Élevée | L89: Elévage | M89: Élevage et productions animales | N89: FR | O89: 47 | P89: Malick Kane | Q89: Sénégal | R89: a-dakar-leismv-place-la-qualite-de-la-formation-veterinaire-au-coeur-de-son-conseil-detablissement-2026
A90: 1412 | B90: 46230 | C90: 2026 | D90: Guinée-Bissau : l’intelligence artificielle aide à détecter la lèpre chez les chimpanzés sauvages | E90: https://www.africavet.com/article/guinee-bissau-lintelligence-artificielle-aide-a-detecter-la-lepre-chez-les-chimpanzes-sauvages | F90: Guinée-Bissau | H90: Afrique de l'Ouest | I90: National | J90: Champ pays | K90: Élevée | L90: Diseases | M90: Santé animale et maladies | N90: FR | O90: 43 | P90: Malick Kane | Q90: Guinée-Bissau | R90: guinee-bissau-lintelligence-artificielle-aide-a-detecter-la-lepre-chez-les-chimpanzes-sauvages
A91: 1411 | B91: 46230 | C91: 2026 | D91: PRESS RELEASE : 44 African countries gather in Addis Ababa to accelerate the eradication of Peste des petits ruminants (PPR) | E91: https://www.africavet.com/article/press-release-44-african-countries-gather-in-addis-ababa-to-accelerate-the-eradication-of-peste-des-petits-ruminants-ppr | F91: Éthiopie | H91: Afrique de l'Est | I91: National | J91: Champ pays | K91: Élevée | L91: Actualités | M91: Actualités et analyses transversales | N91: EN | O91: 18 | P91: Malick Kane | Q91: Ethiopia | R91: press-release-44-african-countries-gather-in-addis-ababa-to-accelerate-the-eradication-of-peste-des-petits-ruminants-ppr
A92: 1410 | B92: 46230 | C92: 2026 | D92: Restaurer la terre, restaurer l’espoir : le pastoralisme comme solution climatique oubliée | E92: https://www.africavet.com/article/restaurer-la-terre-restaurer-lespoir-le-pastoralisme-comme-solution-climatique-oubliee | F92: Mozambique | H92: Afrique australe | I92: National | J92: Début du texte | K92: Moyenne | L92: Elévage | M92: Élevage et productions animales | N92: FR | O92: 34 | P92: Mac Juliette Johngwe | R92: restaurer-la-terre-restaurer-lespoir-le-pastoralisme-comme-solution-climatique-oubliee
A93: 1408 | B93: 46229 | C93: 2026 | D93: La durabilité et la résilience de la pêche artisanale en Afrique | E93: https://www.africavet.com/article/la-durabilite-et-la-resilience-de-la-peche-artisanale-en-afrique | I93: Continental africain | J93: Portée continentale dans le titre | K93: Élevée | L93: Pêches | M93: Pêches et aquaculture | N93: FR | O93: 36 | P93: Mac Juliette Johngwe | R93: la-durabilite-et-la-resilience-de-la-peche-artisanale-en-afrique
A94: 1407 | B94: 46229 | C94: 2026 | D94: Mortalité des poussins : les erreurs des sept premiers jours qui peuvent ruiner un élevage | E94: https://www.africavet.com/article/mortalite-des-poussins-les-erreurs-des-sept-premiers-jours-qui-peuvent-ruiner-un-elevage | I94: Non attribué | J94: Aucun pays AU détecté | K94: À vérifier | L94: Breaking news | M94: Actualités et analyses transversales | N94: FR | O94: 68 | P94: Malick Kane | R94: mortalite-des-poussins-les-erreurs-des-sept-premiers-jours-qui-peuvent-ruiner-un-elevage
A95: 1406 | B95: 46229 | C95: 2026 | D95: Cameroun : 44 % de la production de viande perdue en deux ans, la génétique brésilienne suffira-t-elle ? | E95: https://www.africavet.com/article/cameroun-44-percent-de-la-production-de-viande-perdue-en-deux-ans-la-genetique-bresilienne-suffira-t-elle | F95: Cameroun | H95: Afrique centrale | I95: National | J95: Titre/slug | K95: Élevée | L95: Sécurité Sanitaire | M95: One Health, zoonoses et santé publique | N95: FR | O95: 31 | P95: Malick Kane | R95: cameroun-44-percent-de-la-production-de-viande-perdue-en-deux-ans-la-genetique-bresilienne-suffira-t-elle
A96: 1405 | B96: 46229 | C96: 2026 | D96: Sevrage des veaux : mieux préparer la séparation pour éviter stress, maladies et pertes de poids | E96: https://www.africavet.com/article/sevrage-des-veaux-mieux-preparer-la-separation-pour-eviter-stress-maladies-et-pertes-de-poids | I96: Non attribué | J96: Aucun pays AU détecté | K96: À vérifier | L96: Services vétérinaires | M96: Actualités et analyses transversales | N96: FR | O96: 42 | P96: Malick Kane | R96: sevrage-des-veaux-mieux-preparer-la-separation-pour-eviter-stress-maladies-et-pertes-de-poids
A97: 1404 | B97: 46229 | C97: 2026 | D97: Pêche en Afrique : femmes et jeunes, piliers encore invisibles de l’économie bleue | E97: https://www.africavet.com/article/peche-en-afrique-femmes-et-jeunes-piliers-encore-invisibles-de-leconomie-bleue | I97: Continental africain | J97: Portée continentale dans le titre | K97: Élevée | L97: Pêches | M97: Pêches et aquaculture | N97: FR | O97: 111 | P97: Malick Kane | R97: peche-en-afrique-femmes-et-jeunes-piliers-encore-invisibles-de-leconomie-bleue
A98: 1403 | B98: 46229 | C98: 2026 | D98: Kenya: West Pokot launches cross-border vaccination against PPR and CCPP | E98: https://www.africavet.com/article/kenya-west-pokot-launches-cross-border-vaccination-against-ppr-and-ccpp | F98: Kenya | H98: Afrique de l'Est | I98: National | J98: Titre/slug | K98: Élevée | L98: Elévage | M98: Élevage et productions animales | N98: EN | O98: 70 | P98: Malick Kane | R98: kenya-west-pokot-launches-cross-border-vaccination-against-ppr-and-ccpp
A99: 1402 | B99: 46229 | C99: 2026 | D99: Nigeria : un projet d’usine de vaccins vétérinaires à 100 millions de dollars | E99: https://www.africavet.com/article/nigeria-un-projet-dusine-de-vaccins-veterinaires-a-100-millions-de-dollars | F99: Nigeria | H99: Afrique de l'Ouest | I99: National | J99: Titre/slug | K99: Élevée | L99: Breaking news | M99: Actualités et analyses transversales | N99: FR | O99: 53 | P99: Malick Kane | R99: nigeria-un-projet-dusine-de-vaccins-veterinaires-a-100-millions-de-dollars
A100: 1401 | B100: 46228 | C100: 2026 | D100: Sécheresse et élevage : le Kenya, l’Ouganda et la Somalie misent sur l’assurance climatique | E100: https://www.africavet.com/article/secheresse-et-elevage-le-kenya-louganda-et-la-somalie-misent-sur-lassurance-climatique | F100: Kenya | G100: Somalie; Ouganda | H100: Afrique de l'Est | I100: Multinational africain | J100: Titre/slug | K100: Élevée | L100: Breaking news | M100: Actualités et analyses transversales | N100: FR | O100: 64 | P100: Malick Kane | R100: secheresse-et-elevage-le-kenya-louganda-et-la-somalie-misent-sur-lassurance-climatique
...

Sheet Analyse régions
A1: Répartition régionale des articles nationaux
A2: Les régions sont utilisées comme regroupement éditorial; le classement pays demeure l’unité de référence
A4: Région | B4: Pays UA | C4: Articles nationaux | D4: Part | E4: Moyenne par pays | F4: 12 derniers mois | G4: Pays sans article
A5: Afrique centrale | B5: 9 | C5: =SUMIF('Classement 55'!$C$5:$C$59,A5,'Classement 55'!$D$5:$D$59) -> 163 | D5: =IFERROR(C5/SUM($C$5:$C$9),0) -> 0.29582577 | E5: =IFERROR(C5/B5,0) -> 18.111111 | F5: =SUMIF('Classement 55'!$C$5:$C$59,A5,'Classement 55'!$J$5:$J$59) -> 48 | G5: =COUNTIFS('Classement 55'!$C$5:$C$59,A5,'Classement 55'!$D$5:$D$59,0) -> 1
A6: Afrique de l'Ouest | B6: 15 | C6: =SUMIF('Classement 55'!$C$5:$C$59,A6,'Classement 55'!$D$5:$D$59) -> 214 | D6: =IFERROR(C6/SUM($C$5:$C$9),0) -> 0.38838475 | E6: =IFERROR(C6/B6,0) -> 14.266667 | F6: =SUMIF('Classement 55'!$C$5:$C$59,A6,'Classement 55'!$J$5:$J$59) -> 68 | G6: =COUNTIFS('Classement 55'!$C$5:$C$59,A6,'Classement 55'!$D$5:$D$59,0) -> 0
A7: Afrique de l'Est | B7: 13 | C7: =SUMIF('Classement 55'!$C$5:$C$59,A7,'Classement 55'!$D$5:$D$59) -> 96 | D7: =IFERROR(C7/SUM($C$5:$C$9),0) -> 0.17422868 | E7: =IFERROR(C7/B7,0) -> 7.3846154 | F7: =SUMIF('Classement 55'!$C$5:$C$59,A7,'Classement 55'!$J$5:$J$59) -> 45 | G7: =COUNTIFS('Classement 55'!$C$5:$C$59,A7,'Classement 55'!$D$5:$D$59,0) -> 1
A8: Afrique australe | B8: 10 | C8: =SUMIF('Classement 55'!$C$5:$C$59,A8,'Classement 55'!$D$5:$D$59) -> 41 | D8: =IFERROR(C8/SUM($C$5:$C$9),0) -> 0.074410163 | E8: =IFERROR(C8/B8,0) -> 4.1 | F8: =SUMIF('Classement 55'!$C$5:$C$59,A8,'Classement 55'!$J$5:$J$59) -> 27 | G8: =COUNTIFS('Classement 55'!$C$5:$C$59,A8,'Classement 55'!$D$5:$D$59,0) -> 0
A9: Afrique du Nord | B9: 8 | C9: =SUMIF('Classement 55'!$C$5:$C$59,A9,'Classement 55'!$D$5:$D$59) -> 37 | D9: =IFERROR(C9/SUM($C$5:$C$9),0) -> 0.067150635 | E9: =IFERROR(C9/B9,0) -> 4.625 | F9: =SUMIF('Classement 55'!$C$5:$C$59,A9,'Classement 55'!$J$5:$J$59) -> 18 | G9: =COUNTIFS('Classement 55'!$C$5:$C$59,A9,'Classement 55'!$D$5:$D$59,0) -> 2

Sheet Thèmes et années
A1: Structure thématique et évolution du corpus
A2: Comptes calculés sur les 1 044 pages de type /article/ publiées au 25 août 2026
A4: Macrothèmes | B4: Macrothèmes | C4: Macrothèmes | E4: Évolution annuelle | F4: Évolution annuelle | G4: Évolution annuelle | I4: Portée géographique | J4: Portée géographique | K4: Portée géographique
A5: Macrothème | B5: Articles | C5: Part | E5: Année | F5: Articles | G5: Croissance | I5: Portée | J5: Articles | K5: Part
A6: Actualités et analyses transversales | B6: =COUNTIF(Corpus!$M$2:$M$1045,A6) -> 315 | C6: =B6/SUM($B$6:$B$13) -> 0.30172414 | E6: 2019 | F6: =COUNTIF(Corpus!$C$2:$C$1045,E6) -> 8 | I6: National | J6: =COUNTIF(Corpus!$I$2:$I$1045,I6) -> 551 | K6: =J6/SUM($J$6:$J$11) -> 0.52777778
A7: One Health, zoonoses et santé publique | B7: =COUNTIF(Corpus!$M$2:$M$1045,A7) -> 224 | C7: =B7/SUM($B$6:$B$13) -> 0.21455939 | E7: 2020 | F7: =COUNTIF(Corpus!$C$2:$C$1045,E7) -> 7 | G7: =IFERROR(F7/F6-1,0) -> -0.125 | I7: Non attribué | J7: =COUNTIF(Corpus!$I$2:$I$1045,I7) -> 196 | K7: =J7/SUM($J$6:$J$11) -> 0.18773946
A8: Santé animale et maladies | B8: =COUNTIF(Corpus!$M$2:$M$1045,A8) -> 139 | C8: =B8/SUM($B$6:$B$13) -> 0.13314176 | E8: 2021 | F8: =COUNTIF(Corpus!$C$2:$C$1045,E8) -> 11 | G8: =IFERROR(F8/F7-1,0) -> 0.57142857 | I8: Continental africain | J8: =COUNTIF(Corpus!$I$2:$I$1045,I8) -> 159 | K8: =J8/SUM($J$6:$J$11) -> 0.15229885
A9: Pêches et aquaculture | B9: =COUNTIF(Corpus!$M$2:$M$1045,A9) -> 107 | C9: =B9/SUM($B$6:$B$13) -> 0.10249042 | E9: 2022 | F9: =COUNTIF(Corpus!$C$2:$C$1045,E9) -> 70 | G9: =IFERROR(F9/F8-1,0) -> 5.3636364 | I9: Multinational africain | J9: =COUNTIF(Corpus!$I$2:$I$1045,I9) -> 73 | K9: =J9/SUM($J$6:$J$11) -> 0.069923372
A10: Élevage et productions animales | B10: =COUNTIF(Corpus!$M$2:$M$1045,A10) -> 104 | C10: =B10/SUM($B$6:$B$13) -> 0.099616858 | E10: 2023 | F10: =COUNTIF(Corpus!$C$2:$C$1045,E10) -> 138 | G10: =IFERROR(F10/F9-1,0) -> 0.97142857 | I10: Régional africain | J10: =COUNTIF(Corpus!$I$2:$I$1045,I10) -> 49 | K10: =J10/SUM($J$6:$J$11) -> 0.046934866
A11: Profession et services vétérinaires | B11: =COUNTIF(Corpus!$M$2:$M$1045,A11) -> 73 | C11: =B11/SUM($B$6:$B$13) -> 0.069923372 | E11: 2024 | F11: =COUNTIF(Corpus!$C$2:$C$1045,E11) -> 267 | G11: =IFERROR(F11/F10-1,0) -> 0.93478261 | I11: Hors Afrique / international | J11: =COUNTIF(Corpus!$I$2:$I$1045,I11) -> 16 | K11: =J11/SUM($J$6:$J$11) -> 0.01532567
A12: Ressources, recherche et opportunités | B12: =COUNTIF(Corpus!$M$2:$M$1045,A12) -> 67 | C12: =B12/SUM($B$6:$B$13) -> 0.064176245 | E12: 2025 | F12: =COUNTIF(Corpus!$C$2:$C$1045,E12) -> 242 | G12: =IFERROR(F12/F11-1,0) -> -0.093632959
A13: Faune et conservation | B13: =COUNTIF(Corpus!$M$2:$M$1045,A13) -> 15 | C13: =B13/SUM($B$6:$B$13) -> 0.014367816 | E13: 2026 | F13: =COUNTIF(Corpus!$C$2:$C$1045,E13) -> 301 | G13: =IFERROR(F13/F12-1,0) -> 0.24380165

Sheet Auteurs
A1: Auteurs — contribution, audience et spécialisation
A2: Les variantes d’espacement des noms ont été normalisées; les chiffres restent une photographie cumulative
A4: Auteur | B4: Articles | C4: Part articles | D4: Vues | E4: Part vues | F4: Vues/article | G4: Médiane vues | H4: Impact moyen | I4: Articles fort impact | J4: Complétude moyenne | K4: Articles 2026 | L4: 90 derniers jours | M4: Part EN | N4: Pays couverts | O4: Thème dominant | P4: Article le plus vu
A5: Malick Kane | B5: 798 | C5: 0.76436782 | D5: 17485 | E5: 0.76735715 | F5: 21.911028 | G5: 16 | H5: 48.585965 | I5: 183 | J5: 22.781955 | K5: 241 | L5: 147 | M5: 0.39223058 | N5: 49 | O5: Actualités et analyses transversales | P5: ZLECAf : les ministres africains veulent accélérer le commerce du bétail et transformer l’économie pastorale (226 vues)
A6: Flora J. Ingah | B6: 87 | C6: 0.083333333 | D6: 1758 | E6: 0.077152638 | F6: 20.206897 | G6: 17 | H6: 51.087356 | I6: 11 | J6: 17.931034 | K6: 4 | L6: 0 | M6: 0.34482759 | N6: 17 | O6: Actualités et analyses transversales | P6: South Africa launches “FMD-free with vaccination” roadmap, with mass roll-out from February 2026 (94 vues)
A7: Mac Juliette Johngwe | B7: 85 | C7: 0.081417625 | D7: 2074 | E7: 0.091020802 | F7: 24.4 | G7: 23 | H7: 63.330588 | I7: 33 | J7: 20.470588 | K7: 45 | L7: 29 | M7: 0.37647059 | N7: 21 | O7: Actualités et analyses transversales | P7: Bridging Innovation and Ecology: The Dual Path to Livestock Productivity in Africa (154 vues)
A8: Simon Yaya | B8: 67 | C8: 0.064176245 | D8: 1407 | E8: 0.061748442 | F8: 21 | G8: 18 | H8: 51.950746 | I8: 13 | J8: 17.313433 | K8: 11 | L8: 0 | M8: 0.13432836 | N8: 13 | O8: Actualités et analyses transversales | P8: Tchad : L'élevage, pilier de l'économie, face aux défis et opportunités du développement (71 vues)
A9: Absan Bibou | B9: 7 | C9: 0.0067049808 | D9: 62 | E9: 0.002720969 | F9: 8.8571429 | G9: 8 | H9: 17.085714 | I9: 0 | J9: 21.428571 | K9: 0 | L9: 0 | M9: 0.14285714 | N9: 2 | O9: One Health, zoonoses et santé publique | P9: Africa CDC : 1ère Conférence Internationale sur la Santé Publique en Afrique (17 vues)
A12: Lecture managériale | B12: Lecture managériale | C12: Lecture managériale | D12: Lecture managériale | E12: Lecture managériale | F12: Lecture managériale | G12: Lecture managériale | H12: Lecture managériale
A13: • Malick Kane assure 798 articles sur 1 044 et couvre 49 pays dans les articles nationaux. • Mac Juliette Johngwe obtient la meilleure moyenne brute avec 24,4 vues par article; les différences de récence doivent toutefois être prises en compte. • Le score d’impact moyen le plus élevé appartient à Mac Juliette Johngwe (63,3 / 100). • Utiliser ces données pour répartir les sujets et le mentorat, jamais comme évaluation individuelle isolée sans contexte de commande, d’ancienneté et de format.

Sheet Audience et impact
A1: Audience et impact éditorial
A2: Les vues sont des compteurs cumulés par article; elles ne correspondent pas à des visiteurs uniques
A4: 22786 | E4: 21.82567 | I4: 16.5 | M4: 226
A8: Vues cumulées | E8: Vues moyennes/article | I8: Médiane des vues | M8: Maximum observé
A10: Audience par année de publication | B10: Audience par année de publication | C10: Audience par année de publication | D10: Audience par année de publication | E10: Audience par année de publication | F10: Audience par année de publication
A11: Année | B11: Articles | C11: Vues | D11: Vues/article | E11: Impact moyen | F11: Complétude
A12: 2019 | B12: 8 | C12: 115 | D12: 14.375 | E12: 24.1625 | F12: 18.75
A13: 2020 | B13: 7 | C13: 74 | D13: 10.571429 | E13: 21.257143 | F13: 17.142857
A14: 2021 | B14: 11 | C14: 90 | D14: 8.1818182 | E14: 16.363636 | F14: 19.090909
A15: 2022 | B15: 70 | C15: 951 | D15: 13.585714 | E15: 26.662857 | F15: 16.714286
A16: 2023 | B16: 138 | C16: 1845 | D16: 13.369565 | E16: 30.155072 | F16: 17.608696
A17: 2024 | B17: 267 | C17: 3831 | D17: 14.348315 | E17: 36.239326 | F17: 17.902622
A18: 2025 | B18: 242 | C18: 4877 | D18: 20.152893 | E18: 52.480579 | F18: 17.933884
A19: 2026 | B19: 301 | C19: 11003 | D19: 36.554817 | E19: 77.320598 | F19: 31.860465
A23: Audience par macrothème | B23: Audience par macrothème | C23: Audience par macrothème | D23: Audience par macrothème | E23: Audience par macrothème | F23: Audience par macrothème
A24: Macrothème | B24: Articles | C24: Vues | D24: Vues/article | E24: Impact moyen | F24: Complétude
A25: Actualités et analyses transversales | B25: 315 | C25: 6830 | D25: 21.68254 | E25: 48.603175 | F25: 21.111111
A26: One Health, zoonoses et santé publique | B26: 224 | C26: 4381 | D26: 19.558036 | E26: 47.201339 | F26: 20.625
A27: Santé animale et maladies | B27: 139 | C27: 3626 | D27: 26.086331 | E27: 56.951079 | F27: 25.539568
A28: Élevage et productions animales | B28: 104 | C28: 2368 | D28: 22.769231 | E28: 53.872115 | F28: 24.519231
A29: Ressources, recherche et opportunités | B29: 67 | C29: 1914 | D29: 28.567164 | E29: 58.402985 | F29: 20.597015
A30: Pêches et aquaculture | B30: 107 | C30: 1799 | D30: 16.813084 | E30: 39.837383 | F30: 20.373832
A31: Profession et services vétérinaires | B31: 73 | C31: 1507 | D31: 20.643836 | E31: 51.472603 | F31: 20
A32: Faune et conservation | B32: 15 | C32: 361 | D32: 24.066667 | E32: 57.633333 | F32: 26.666667
A44: Ce que le corpus mesure — et ce qu’il ne mesure pas | B44: Ce que le corpus mesure — et ce qu’il ne mesure pas | C44: Ce que le corpus mesure — et ce qu’il ne mesure pas | D44: Ce que le corpus mesure — et ce qu’il ne mesure pas | E44: Ce que le corpus mesure — et ce qu’il ne mesure pas | F44: Ce que le corpus mesure — et ce qu’il ne mesure pas | G44: Ce que le corpus mesure — et ce qu’il ne mesure pas | H44: Ce que le corpus mesure — et ce qu’il ne mesure pas | I44: Ce que le corpus mesure — et ce qu’il ne mesure pas | J44: Ce que le corpus mesure — et ce qu’il ne mesure pas | K44: Ce que le corpus mesure — et ce qu’il ne mesure pas | L44: Ce que le corpus mesure — et ce qu’il ne mesure pas | M44: Ce que le corpus mesure — et ce qu’il ne mesure pas | N44: Ce que le corpus mesure — et ce qu’il ne mesure pas | O44: Ce que le corpus mesure — et ce qu’il ne mesure pas | P44: Ce que le corpus mesure — et ce qu’il ne mesure pas
A45: Indicateur | B45: Disponible | C45: Source nécessaire | D45: Utilité
A46: Vues cumulées par article | B46: Oui | C46: API AfricaVET | D46: Audience brute et comparaisons relatives
A47: Visiteurs uniques | B47: Non | C47: GA4 ou Matomo requis | D47: Mesurer la taille réelle de l’audience
A48: Sessions et pages par session | B48: Non | C48: GA4 ou Matomo requis | D48: Mesurer la profondeur de consultation
A49: Sources de trafic | B49: Non | C49: GA4/Matomo + UTM | D49: Comparer recherche, réseaux sociaux et accès direct
A50: Pays et villes des visiteurs | B50: Non | C50: GA4 ou Matomo requis | D50: Mesurer la portée panafricaine réelle
A51: Temps d’engagement | B51: Non | C51: GA4 ou Matomo requis | D51: Évaluer la lecture effective des articles
A52: Partages et clics sociaux | B52: Non | C52: Plateformes sociales + UTM | D52: Mesurer l’amplification éditoriale
A53: Conversions | B53: Non | C53: Événements analytics | D53: Newsletter, WhatsApp, téléchargements et contacts

Sheet Performance articles
A1: Performance détaillée des articles
A2: Impact relatif = vues cumulées et vitesse d’acquisition; complétude = présence des éléments journalistiques et SEO
A4: Rang impact | B4: Rang vues | C4: ID | D4: Date | E4: Titre | F4: Auteur | G4: Pays principal | H4: Portée | I4: Macrothème | J4: Langue | K4: Vues | L4: Âge (jours) | M4: Vues/jour | N4: Score impact | O4: Niveau impact | P4: Mots | Q4: Complétude /100 | R4: Critères manquants | S4: URL
A5: 1 | B5: 2 | C5: 1471 | D5: 46254 | E5: Coccidiose chez les poulets : ces signes discrets qui peuvent coûter cher à l’éleveur | F5: Malick Kane | G5: Non attribué | H5: Non attribué | I5: Ressources, recherche et opportunités | J5: FR | K5: 181 | L5: 5 | M5: 30.166667 | N5: 99.9 | O5: Très fort | P5: 1210 | Q5: 40 | R5: Titre de 45 à 80 caractères; Résumé de 120 à 220 caractères; Crédit ou source de l’image; Pays ou région renseigné; Sources journalistiques renseignées; Relecture ou vérification tracée | S5: https://www.africavet.com/article/coccidiose-chez-les-poulets-ces-signes-discrets-qui-peuvent-couter-cher-a-leleveur
A6: 2 | B6: 5 | C6: 1474 | D6: 46255 | E6: Burkina Faso : l’opération « Zéro poulailler vide » veut remettre 500 élevages avicoles en production | F6: Malick Kane | G6: Burkina Faso | H6: National | I6: Actualités et analyses transversales | J6: FR | K6: 121 | L6: 4 | M6: 24.2 | N6: 99.7 | O6: Très fort | P6: 570 | Q6: 50 | R6: Titre de 45 à 80 caractères; Résumé de 120 à 220 caractères; Crédit ou source de l’image; Sources journalistiques renseignées; Relecture ou vérification tracée | S6: https://www.africavet.com/article/burkina-faso-loperation-zero-poulailler-vide-veut-remettre-500-elevages-avicoles-en-production
A7: 3 | B7: 10 | C7: 1470 | D7: 46254 | E7: PPR : les « épisystèmes », un levier stratégique pour le PAPS et l’éradication en Afrique | F7: Malick Kane | G7: Non attribué | H7: Continental africain | I7: Actualités et analyses transversales | J7: FR | K7: 91 | L7: 5 | M7: 15.166667 | N7: 99.3 | O7: Très fort | P7: 2881 | Q7: 40 | R7: Titre de 45 à 80 caractères; Résumé de 120 à 220 caractères; Crédit ou source de l’image; Pays ou région renseigné; Sources journalistiques renseignées; Relecture ou vérification tracée | S7: https://www.africavet.com/article/ppr-les-episystemes-un-levier-strategique-pour-le-paps-et-leradication-en-afrique
A8: 4 | B8: 1 | C8: 1376 | D8: 46220 | E8: ZLECAf : les ministres africains veulent accélérer le commerce du bétail et transformer l’économie pastorale | F8: Malick Kane | G8: Éthiopie | H8: National | I8: Actualités et analyses transversales | J8: FR | K8: 226 | L8: 39 | M8: 5.65 | N8: 99.2 | O8: Très fort | P8: 1171 | Q8: 60 | R8: Titre de 45 à 80 caractères; Résumé de 120 à 220 caractères; Sources journalistiques renseignées; Relecture ou vérification tracée | S8: https://www.africavet.com/article/zlecaf-les-ministres-africains-veulent-accelerer-le-commerce-du-betail-et-transformer-leconomie-pastorale
A9: 5 | B9: 15 | C9: 1473 | D9: 46255 | E9: Cameroun : 93 stages ouverts dans des projets financés par la BAD, dont huit au PDCVEP | F9: Malick Kane | G9: Cameroun | H9: National | I9: Ressources, recherche et opportunités | J9: FR | K9: 75 | L9: 4 | M9: 15 | N9: 99 | O9: Très fort | P9: 894 | Q9: 50 | R9: Titre de 45 à 80 caractères; Résumé de 120 à 220 caractères; Crédit ou source de l’image; Sources journalistiques renseignées; Relecture ou vérification tracée | S9: https://www.africavet.com/article/cameroun-93-stages-ouverts-dans-des-projets-finances-par-la-bad-dont-huit-au-pdcvep
A10: 6 | B10: 6 | C10: 1404 | D10: 46229 | E10: Pêche en Afrique : femmes et jeunes, piliers encore invisibles de l’économie bleue | F10: Malick Kane | G10: Non attribué | H10: Continental africain | I10: Pêches et aquaculture | J10: FR | K10: 111 | L10: 30 | M10: 3.5806452 | N10: 98.3 | O10: Très fort | P10: 595 | Q10: 40 | R10: Titre de 45 à 80 caractères; Résumé de 120 à 220 caractères; Crédit ou source de l’image; Pays ou région renseigné; Sources journalistiques renseignées; Relecture ou vérification tracée | S10: https://www.africavet.com/article/peche-en-afrique-femmes-et-jeunes-piliers-encore-invisibles-de-leconomie-bleue
A11: 7 | B11: 4 | C11: 1364 | D11: 46214 | E11: Peste des petits ruminants : symptômes, transmission, diagnostic, vaccination et prévention | F11: Malick Kane | G11: Non attribué | H11: Continental africain | I11: Actualités et analyses transversales | J11: FR | K11: 145 | L11: 45 | M11: 3.1521739 | N11: 98.2 | O11: Très fort | P11: 3152 | Q11: 30 | R11: Titre de 45 à 80 caractères; Crédit ou source de l’image; Pays ou région renseigné; Méta-titre SEO renseigné; Méta-description SEO renseignée; Sources journalistiques renseignées; Relecture ou vérification tracée | S11: https://www.africavet.com/article/peste-des-petits-ruminants-symptomes-diagnostic-vaccination-prevention
A12: 8 | B12: 11 | C12: 1422 | D12: 46235 | E12: Sénégal : à Mbao, 1 000 ruches pour donner un nouvel élan à l’apiculture | F12: Malick Kane | G12: Sénégal | H12: National | I12: One Health, zoonoses et santé publique | J12: FR | K12: 89 | L12: 24 | M12: 3.56 | N12: 98 | O12: Très fort | P12: 506 | Q12: 60 | R12: Résumé de 120 à 220 caractères; Crédit ou source de l’image; Sources journalistiques renseignées; Relecture ou vérification tracée | S12: https://www.africavet.com/article/senegal-a-mbao-1-000-ruches-pour-donner-un-nouvel-elan-a-lapiculture
A13: 9 | B13: 14 | C13: 1426 | D13: 46236 | E13: Sudan: Vaccinating livestock amid conflict, a cross-border logistical challenge | F13: Malick Kane | G13: Soudan | H13: National | I13: Santé animale et maladies | J13: EN | K13: 78 | L13: 23 | M13: 3.25 | N13: 97.8 | O13: Très fort | P13: 779 | Q13: 50 | R13: Résumé de 120 à 220 caractères; Crédit ou source de l’image; Pays ou région renseigné; Sources journalistiques renseignées; Relecture ou vérification tracée | S13: https://www.africavet.com/article/sudan-vaccinating-livestock-amid-conflict-a-cross-border-logistical-challenge
A14: 10 | B14: 25 | C14: 1455 | D14: 46248 | E14: Fientes anormales chez les poulets : ce que leur couleur peut révéler — et ce qu’elle ne permet pas de diagnostiquer | F14: Malick Kane | G14: Non attribué | H14: Non attribué | I14: Ressources, recherche et opportunités | J14: FR | K14: 66 | L14: 11 | M14: 5.5 | N14: 97.7 | O14: Très fort | P14: 1112 | Q14: 40 | R14: Titre de 45 à 80 caractères; Résumé de 120 à 220 caractères; Crédit ou source de l’image; Pays ou région renseigné; Sources journalistiques renseignées; Relecture ou vérification tracée | S14: https://www.africavet.com/article/fientes-anormales-chez-les-poulets-ce-que-leur-couleur-peut-reveler-et-ce-quelle-ne-permet-pas-de-diagnostiquer
A15: 11 | B15: 8 | C15: 1391 | D15: 46224 | E15: Grippe aviaire H5N1 : l’Afrique de l’Ouest ne peut plus attendre les premières mortalités | F15: Malick Kane | G15: Non attribué | H15: Régional africain | I15: Santé animale et maladies | J15: FR | K15: 97 | L15: 35 | M15: 2.6944444 | N15: 97.6 | O15: Très fort | P15: 1792 | Q15: 50 | R15: Titre de 45 à 80 caractères; Résumé de 120 à 220 caractères; Crédit ou source de l’image; Sources journalistiques renseignées; Relecture ou vérification tracée | S15: https://www.africavet.com/article/grippe-aviaire-h5n1-lafrique-de-louest-ne-peut-plus-attendre-les-premieres-mortalites
A16: 12 | B16: 40 | C16: 1481 | D16: 46256 | E16: Cameroun : 6,5 milliards FCFA supplémentaires pour financer l’élevage bovin, le lait et le poisson | F16: Malick Kane | G16: Cameroun | H16: National | I16: Élevage et productions animales | J16: FR | K16: 61 | L16: 3 | M16: 15.25 | N16: 97.6 | O16: Très fort | P16: 732 | Q16: 50 | R16: Titre de 45 à 80 caractères; Résumé de 120 à 220 caractères; Crédit ou source de l’image; Sources journalistiques renseignées; Relecture ou vérification tracée | S16: https://www.africavet.com/article/cameroun-65-milliards-fcfa-supplementaires-pour-financer-lelevage-bovin-le-lait-et-le-poisson
... A1048: 1044 | B1048: 1044 | C1048: 145 | D1048: 44869 | E1048: An atlas to support the progressive control of tsetse‑transmitted animal trypanosomosis in Burkina Faso | F1048: Malick Kane | G1048: Burkina Faso | H1048: National | I1048: Santé animale et maladies | J1048: EN | K1048: 0 | L1048: 1390 | M1048: 0 | N1048: 0.4 | O1048: Très faible | P1048: 428 | Q1048: 10 | R1048: Titre de 45 à 80 caractères; Résumé de 120 à 220 caractères; Article d’au moins 500 mots; Crédit ou source de l’image; Pays ou région renseigné; Méta-titre SEO renseigné; Méta-description SEO renseignée; Sources journalistiques renseignées; Relecture ou vérification tracée | S1048: https://www.africavet.com/article/an-atlas-to-support-the-progressive-control-of-tsetse%e2%80%91transmitted-animal-trypanosomosis-in-burkina-faso

Sheet Qualité éditoriale
A1: Qualité éditoriale et complétude des métadonnées
A2: Le score mesure la présence de dix éléments vérifiables; il ne note ni l’exactitude scientifique ni la qualité de l’écriture
A4: 21.829502 | E4: 0.08908046 | I4: 0.099616858 | M4: 0.99712644
A8: Complétude moyenne /100 | E8: Méta-titre renseigné | I8: Méta-description renseignée | M8: Image principale
A10: Contrôle des dix critères | B10: Contrôle des dix critères | C10: Contrôle des dix critères | D10: Contrôle des dix critères
A11: Critère | B11: Conformes | C11: Taux | D11: Écart
A12: Sources journalistiques renseignées | B12: 0 | C12: 0 | D12: 1044
A13: Relecture ou vérification tracée | B13: 0 | C13: 0 | D13: 1044
A14: Crédit ou source de l’image | B14: 2 | C14: 0.0019157088 | D14: 1042
A15: Pays ou région renseigné | B15: 69 | C15: 0.066091954 | D15: 975
A16: Méta-titre SEO renseigné | B16: 93 | C16: 0.08908046 | D16: 951
A17: Méta-description SEO renseignée | B17: 104 | C17: 0.099616858 | D17: 940
A18: Résumé de 120 à 220 caractères | B18: 136 | C18: 0.1302682 | D18: 908
A19: Titre de 45 à 80 caractères | B19: 362 | C19: 0.3467433 | D19: 682
A20: Article d’au moins 500 mots | B20: 472 | C20: 0.45210728 | D20: 572
A21: Image principale renseignée | B21: 1041 | C21: 0.99712644 | D21: 3
A25: Distribution des scores de complétude | B25: Distribution des scores de complétude | C25: Distribution des scores de complétude | D25: Distribution des scores de complétude
A26: Score | B26: Articles
A27: 0–19 | B27: 279
A28: 20–39 | B28: 653
A29: 40–59 | B29: 92
A30: 60–79 | B30: 20
A31: 80–100 | B31: 0
A34: Diagnostic et mesures immédiates | B34: Diagnostic et mesures immédiates | C34: Diagnostic et mesures immédiates | D34: Diagnostic et mesures immédiates | E34: Diagnostic et mesures immédiates | F34: Diagnostic et mesures immédiates | G34: Diagnostic et mesures immédiates | H34: Diagnostic et mesures immédiates | I34: Diagnostic et mesures immédiates | J34: Diagnostic et mesures immédiates | K34: Diagnostic et mesures immédiates | L34: Diagnostic et mesures immédiates | M34: Diagnostic et mesures immédiates | N34: Diagnostic et mesures immédiates
A35: • Aucun article ne possède actuellement de sources structurées dans le champ dédié et aucune relecture/vérification n’est tracée dans les champs correspondants. • Seuls 0,2 % des articles renseignent un crédit ou une source d’image, alors que 99,7 % possèdent une image principale. • Les méta-titres et méta-descriptions ne sont renseignés que pour 8,9 % et 10,0 % du corpus. • Priorité CMS : rendre obligatoires les sources, la provenance de l’image, le pays ou la région, la langue réelle et les champs SEO. • Priorité rédaction : instaurer une validation à deux niveaux pour les contenus sensibles — exactitude factuelle/scientifique puis conformité éditoriale.

Sheet Rythme publication
A1: Rythme de publication et organisation de la rédaction
A2: Analyse des dates et heures de publication; les vues moyennes ne doivent pas être interprétées comme une causalité horaire
A4: Production mensuelle en 2026 | B4: Production mensuelle en 2026 | C4: Production mensuelle en 2026 | D4: Production mensuelle en 2026
A5: Mois | B5: Articles | C5: Vues cumulées | D5: Vues/article
A6: 2026-01 | B6: 33 | C6: 918 | D6: 27.818182
A7: 2026-02 | B7: 20 | C7: 717 | D7: 35.85
A8: 2026-03 | B8: 11 | C8: 204 | D8: 18.545455
A9: 2026-04 | B9: 21 | C9: 503 | D9: 23.952381
A10: 2026-05 | B10: 42 | C10: 1416 | D10: 33.714286
A11: 2026-06 | B11: 21 | C11: 734 | D11: 34.952381
A12: 2026-07 | B12: 71 | C12: 3477 | D12: 48.971831
A13: 2026-08 | B13: 82 | C13: 3034 | D13: 37
A19: Répartition par jour de semaine | B19: Répartition par jour de semaine | C19: Répartition par jour de semaine | D19: Répartition par jour de semaine
A20: Jour | B20: Articles | C20: Vues cumulées | D20: Vues/article
A21: Lundi | B21: 138 | C21: 3278 | D21: 23.753623
A22: Mardi | B22: 147 | C22: 2748 | D22: 18.693878
A23: Mercredi | B23: 122 | C23: 2262 | D23: 18.540984
A24: Jeudi | B24: 107 | C24: 2328 | D24: 21.757009
A25: Vendredi | B25: 162 | C25: 3737 | D25: 23.067901
A26: Samedi | B26: 202 | C26: 4505 | D26: 22.30198
A27: Dimanche | B27: 166 | C27: 3928 | D27: 23.662651
A34: Tranches horaires de publication | B34: Tranches horaires de publication | C34: Tranches horaires de publication | D34: Tranches horaires de publication | F34: Interprétation opérationnelle | G34: Interprétation opérationnelle | H34: Interprétation opérationnelle | I34: Interprétation opérationnelle | J34: Interprétation opérationnelle | K34: Interprétation opérationnelle | L34: Interprétation opérationnelle | M34: Interprétation opérationnelle | N34: Interprétation opérationnelle
A35: Heure UTC | B35: Articles | C35: Vues cumulées | D35: Vues/article | F35: • 2026-08 est le mois le plus productif de 2026 avec 82 articles. • Le samedi et le dimanche totalisent 368 articles, soit 35,2 % du corpus. • Les vues moyennes par jour ou heure sont fortement influencées par l’ancienneté des articles et leur sujet; elles servent à formuler des tests, pas à fixer seules un horaire optimal. • Recommandation : organiser un calendrier hebdomadaire avec des créneaux distincts pour actualités, analyses, guides et opportunités, puis mesurer chaque créneau avec des UTM et des données d’engagement.
A36: 00–05 UTC | B36: 140 | C36: 2494 | D36: 17.814286
A37: 06–11 UTC | B37: 204 | C37: 4792 | D37: 23.490196
A38: 12–17 UTC | B38: 285 | C38: 6376 | D38: 22.37193
A39: 18–23 UTC | B39: 415 | C39: 9124 | D39: 21.985542

Sheet Méthodologie
A1: Méthodologie de classement
A2: Version arrêtée au 25 août 2026 — reproductible à partir du corpus exporté
A4: Périmètre | B4: Périmètre | C4: Périmètre | D4: Périmètre | E4: Périmètre | F4: Périmètre | G4: Périmètre | H4: Périmètre
A5: Corpus : toutes les 1 044 pages publiées retournées par l’API publique AfricaVET /api/posts, dont l’URL canonique contient /article/. Période couverte : 2019-08-30 au 2026-08-25. Les opportunités et formations n’ayant pas le type article ne sont pas intégrées.
A10: Règles d’attribution géographique | B10: Règles d’attribution géographique | C10: Règles d’attribution géographique | D10: Règles d’attribution géographique | E10: Règles d’attribution géographique | F10: Règles d’attribution géographique | G10: Règles d’attribution géographique | H10: Règles d’attribution géographique
A11: 1 | B11: Champ pays | C11: Prioritaire lorsqu’il est renseigné dans le CMS. | D11: Confiance élevée
A12: 2 | B12: Titre/slug | C12: Recherche des noms de pays, variantes FR/EN, gentilés, capitales et principaux toponymes. | D12: Confiance élevée
A13: 3 | B13: Chapeau | C13: Utilisé si le titre ne contient pas d’ancrage africain régional ou continental. | D13: Confiance moyenne
A14: 4 | B14: Début du texte | C14: Attribution contextuelle lorsque le pays n’apparaît qu’au début du contenu. | D14: À réviser
A15: 5 | B15: Portée séparée | C15: Les contenus régionaux, continentaux, multinationaux et hors Afrique ne sont pas forcés dans un pays. | D15: Évite les doubles comptes
A16: 6 | B16: Classement national | C16: Le rang porte sur les articles à portée nationale; les mentions multinationales sont suivies séparément. | D16: Un article national = un pays
A17: 7 | B17: 55 États membres | C17: La table conserve les 55 membres de l’Union africaine, y compris les pays à zéro article. | D17: Exhaustif
A18: 8 | B18: Date d’arrêté | C18: Les résultats changent dès qu’un nouvel article est publié ou qu’une taxonomie est corrigée. | D18: Photographie, non flux temps réel
A20: Limites et contrôles recommandés | B20: Limites et contrôles recommandés | C20: Limites et contrôles recommandés | D20: Limites et contrôles recommandés | E20: Limites et contrôles recommandés | F20: Limites et contrôles recommandés | G20: Limites et contrôles recommandés | H20: Limites et contrôles recommandés
A21: • Le champ country n’est renseigné que pour 61 articles (5,8 %), ce qui limite l’analyse native du CMS. • Le champ original_language vaut “fr” pour tous les articles, alors que la détection textuelle estime 385 articles en anglais : la métadonnée de langue n’est pas fiable. • Certaines pages sont des éditions FR/EN séparées d’un même événement; le classeur compte les articles publiés, pas les événements uniques. • Les attributions contextuelles peuvent refléter le lieu d’un atelier, le siège d’une institution ou un exemple cité plutôt que le pays au cœur du sujet. Elles sont isolées dans une colonne dédiée. • Les titres génériques, ressources mondiales et contenus sans pays explicite restent “Non attribués” au lieu d’être affectés arbitrairement. • Une revue éditoriale manuelle est recommandée pour toutes les lignes “À vérifier” et pour les 50 attributions contextuelles nationales.
A30: Sources | B30: Sources | C30: Sources | D30: Sources | E30: Sources | F30: Sources | G30: Sources | H30: Sources
A31: Source primaire : https://www.africavet.com/api/posts?limit=2000&page=1&sort=created_at&order=DESC Site : https://www.africavet.com/ Référence institutionnelle pour les États membres : https://au.int/en/member_states/countryprofiles2
A36: Indicateurs journalistiques ajoutés | B36: Indicateurs journalistiques ajoutés | C36: Indicateurs journalistiques ajoutés | D36: Indicateurs journalistiques ajoutés | E36: Indicateurs journalistiques ajoutés | F36: Indicateurs journalistiques ajoutés | G36: Indicateurs journalistiques ajoutés | H36: Indicateurs journalistiques ajoutés
A37: Impact relatif : 60 % percentile des vues cumulées + 40 % percentile des vues par jour depuis publication. Ce score compare les articles à l’intérieur du corpus et ne mesure pas un changement social, sanitaire ou politique attribuable à la publication. Complétude éditoriale : 10 critères de complétude à 10 points chacun; mesure les métadonnées et la présentation, pas la qualité du fond. Les dix critères sont visibles dans la feuille “Qualité éditoriale” et les lacunes par article dans “Performance articles”.
A43: Limites de la mesure d’audience | B43: Limites de la mesure d’audience | C43: Limites de la mesure d’audience | D43: Limites de la mesure d’audience | E43: Limites de la mesure d’audience | F43: Limites de la mesure d’audience | G43: Limites de la mesure d’audience | H43: Limites de la mesure d’audience
A44: Le compteur view_count fournit des vues cumulées par article au moment de l’extraction. Il ne permet pas d’identifier les visiteurs uniques, les sessions, les sources de trafic, la localisation de l’audience, le temps d’engagement, les partages sociaux ou les conversions. Les comparaisons par année, auteur et horaire sont descriptives et restent influencées par l’ancienneté, le sujet, la promotion et les mises à jour des articles.
